Workbook

Sheet JVC
A1: B1 JVC
A2: № | B2: Наименование товара | C2: ЦЕНА | D2: НОРМА | E2: ОСТАТОК ПРОШЛОГО ДНЯ | F2: ПРИХОД | G2: ПЕРЕМЕЩЕНИЕ | H2: ОСТАТОК ДОМА | I2: ПРОДАЖА | J2: СУММА | K2: ЗАЯВКА | L2: Доп к заявке | M2: ОСТАТОК ТЕКУЩЕГО ДНЯ
A3: 1 | B3: ABSOLUT BLUE LTR | C3: 100 | D3: 40 | E3: 7 | F3: 23 | H3: 24 | I3: =E3+F3-G3-H3 -> 6 | J3: =C3*I3 -> 600
A4: 2 | B4: J/W RED LABEL 1 LTR | C4: 100 | D4: 40 | E4: 17 | F4: 13 | H4: 28 | I4: =E4+F4-G4-H4 -> 2 | J4: =C4*I4 -> 200
A5: 3 | B5: J/W BLAK LABEL 1 LTR | C5: 200 | D5: 20 | E5: 8 | F5: 6 | H5: 13 | I5: =E5+F5-G5-H5 -> 1 | J5: =C5*I5 -> 200
A6: 4 | B6: JACK DANIELS LTR | C6: 200 | D6: 20 | E6: 6 | F6: 4 | H6: 10 | I6: =E6+F6-G6-H6 -> 0 | J6: =C6*I6 -> 0
A7: 5 | B7: CHIVAS REGAL 1 LTR | C7: 200 | D7: 20 | E7: 26 | F7: 10 | H7: 35 | I7: =E7+F7-G7-H7 -> 1 | J7: =C7*I7 -> 200
A8: 6 | B8: HEINEKEN BEER CANS 33CL | C8: 200 | D8: 15 | E8: 1 | F8: 6 | H8: 6 | I8: =E8+F8-G8-H8 -> 1 | J8: =C8*I8 -> 200
A9: 7 | B9: BUDWEISER BEER CAN 33/35 | C9: 200 | D9: 12 | E9: 4.5 | F9: 3.5 | H9: 7.5 | I9: =E9+F9-G9-H9 -> 0.5 | J9: =C9*I9 -> 100
A10: 8 | B10: CARLSBERG 50CL Can | C10: 200 | D10: 8 | E10: 2.5 | F10: 4.5 | H10: 4.5 | I10: =E10+F10-G10-H10 -> 2.5 | J10: =C10*I10 -> 500
A11: 9 | B11: RED HORSE 50CL Can | C11: 200 | D11: 5 | E11: 7.5 | H11: 7.5 | I11: =E11+F11-G11-H11 -> 0 | J11: =C11*I11 -> 0
A12: 10 | B12: AMSTEL LIGHT Slim Can 35 | C12: 200 | D12: 5 | E12: 1 | H12: 1 | I12: =E12+F12-G12-H12 -> 0 | J12: =C12*I12 -> 0
A13: 11 | B13: CORONA BEER BTL 35.5CL | C13: 300 | D13: 10 | E13: 2 | F13: 6 | H13: 7.5 | I13: =E13+F13-G13-H13 -> 0.5 | J13: =C13*I13 -> 150
A14: 12 | B14: STELLA 33CL BTLS | C14: 300 | D14: 2 | E14: 2 | H14: 2 | I14: =E14+F14-G14-H14 -> 0 | J14: =C14*I14 -> 0
A15: 13 | B15: STELLA ARTOIS 33 CL cans | C15: 200 | D15: 5 | E15: 0.5 | F15: 1.5 | H15: 2 | I15: =E15+F15-G15-H15 -> 0 | J15: =C15*I15 -> 0
A16: 14 | B16: HEINEKEN BEER BTL 33CL | C16: 300 | D16: 1.5 | E16: 1 | F16: 1 | H16: 2 | I16: =E16+F16-G16-H16 -> 0 | J16: =C16*I16 -> 0
A17: 15 | B17: BUDWEISER BERR BTL 33cl | C17: 300 | D17: 1.5 | E17: 2 | H17: 2 | I17: =E17+F17-G17-H17 -> 0 | J17: =C17*I17 -> 0
A18: 16 | B18: SMIRNOFF ICE RED 27,5CL | C18: 300 | D18: 1.5 | E18: 1.5 | F18: 0.5 | H18: 1 | I18: =E18+F18-G18-H18 -> 1 | J18: =C18*I18 -> 300
A19: 17 | B19: PERONI NASTRO AZURO BEER | C19: 300 | D19: 1 | E19: 0.5 | F19: 1.5 | H19: 2 | I19: =E19+F19-G19-H19 -> 0 | J19: =C19*I19 -> 0
A20: 18 | B20: JC CHARDONNAY 75CL | C20: 100 | D20: 20 | E20: 0 | H20: 0 | I20: =E20+F20-G20-H20 -> 0 | J20: =C20*I20 -> 0
A21: 19 | B21: JC SHIRAZ CABARNET 75CL | C21: 100 | D21: 20 | E21: 15 | H21: 14 | I21: =E21+F21-G21-H21 -> 1 | J21: =C21*I21 -> 100
A22: 20 | B22: CES PINOT GRIG D VEN FIO | C22: 100 | D22: 20 | E22: 7 | F22: 13 | H22: 20 | I22: =E22+F22-G22-H22 -> 0 | J22: =C22*I22 -> 0
A23: 21 | B23: Le GRAND Noir SAUV BLANC | C23: 100 | D23: 20 | E23: 6 | F23: 14 | H23: 17 | I23: =E23+F23-G23-H23 -> 3 | J23: =C23*I23 -> 300
A24: 22 | B24: Le GRAND Noir MERLOT 75C | C24: 100 | D24: 15 | E24: 11 | F24: 9 | H24: 20 | I24: =E24+F24-G24-H24 -> 0 | J24: =C24*I24 -> 0
A25: 23 | B25: MIP Collection ROSE Provienc 7 | C25: 150 | D25: 3 | E25: 1 | H25: 1 | I25: =E25+F25-G25-H25 -> 0 | J25: =C25*I25 -> 0
A26: 24 | B26: CH KSARA SUNSET ROSE 75C | C26: 100 | D26: 15 | E26: 5 | H26: 5 | I26: =E26+F26-G26-H26 -> 0 | J26: =C26*I26 -> 0
A27: 25 | B27: MATEUS ROSE 75CL | C27: 100 | D27: 15 | E27: 1 | F27: 6 | H27: 7 | I27: =E27+F27-G27-H27 -> 0 | J27: =C27*I27 -> 0
A28: 26 | B28: BACARDI WHITE RUM LTR | C28: 100 | D28: 15 | E28: 2 | F28: 4 | H28: 6 | I28: =E28+F28-G28-H28 -> 0 | J28: =C28*I28 -> 0
A29: 27 | B29: BACARDI BLACK. 1 LTR | C29: 100 | D29: 6 | E29: 6 | H29: 6 | I29: =E29+F29-G29-H29 -> 0 | J29: =C29*I29 -> 0
A30: 28 | B30: BACARDI GOLD LTR | C30: 100 | D30: 8 | E30: 4 | F30: 2 | H30: 6 | I30: =E30+F30-G30-H30 -> 0 | J30: =C30*I30 -> 0
A31: 29 | B31: JOSE CUERVO GOLD LTR | C31: 100 | D31: 10 | E31: 6 | F31: 4 | H31: 8 | I31: =E31+F31-G31-H31 -> 2 | J31: =C31*I31 -> 200
A32: 30 | B32: JOSE CUERVO SILVER Espec | C32: 100 | D32: 10 | E32: 3 | F32: 7 | H32: 10 | I32: =E32+F32-G32-H32 -> 0 | J32: =C32*I32 -> 0
A33: 31 | B33: TANQUERAY GIN LTR | C33: 200 | D33: 2 | E33: 3 | H33: 3 | I33: =E33+F33-G33-H33 -> 0 | J33: =C33*I33 -> 0
A34: 32 | B34: GORDONS PINK GIN Ltr | C34: 150 | D34: 6 | E34: 3 | H34: 3 | I34: =E34+F34-G34-H34 -> 0 | J34: =C34*I34 -> 0
A35: 33 | B35: GORDONS GIN LTR | C35: 100 | D35: 12 | E35: 0 | F35: 10 | H35: 9 | I35: =E35+F35-G35-H35 -> 1 | J35: =C35*I35 -> 100
A36: 34 | B36: BOMBAY SAPPHIRE GIN LTR | C36: 150 | D36: 12 | E36: 2 | F36: 8 | H36: 8 | I36: =E36+F36-G36-H36 -> 2 | J36: =C36*I36 -> 300
A37: 35 | B37: HENDRICKS GIN 1 LTR | C37: 250 | D37: 10 | E37: 7 | H37: 7 | I37: =E37+F37-G37-H37 -> 0 | J37: =C37*I37 -> 0
A38: 36 | B38: CAPTAIN MORGAN BLK LTR | C38: 150 | D38: 3 | E38: 7 | H38: 7 | I38: =E38+F38-G38-H38 -> 0 | J38: =C38*I38 -> 0
A39: 37 | B39: CAPTAIN MORGAN SPICED GO | C39: 150 | D39: 3 | E39: 4 | F39: 3 | H39: 7 | I39: =E39+F39-G39-H39 -> 0 | J39: =C39*I39 -> 0
A40: 38 | B40: MALIBU WHITHE RUM LTR | C40: 150 | D40: 5 | E40: 2 | H40: 2 | I40: =E40+F40-G40-H40 -> 0 | J40: =C40*I40 -> 0
A41: 39 | B41: BAILEYS IRISH CREAM LTR | C41: 150 | D41: 6 | E41: 6 | H41: 6 | I41: =E41+F41-G41-H41 -> 0 | J41: =C41*I41 -> 0
A42: 40 | B42: AMARULA CREAM LTR | C42: 150 | D42: 2 | E42: 2 | H42: 2 | I42: =E42+F42-G42-H42 -> 0 | J42: =C42*I42 -> 0
A43: 41 | B43: JAMESON IRISH WSK LTR | C43: 200 | D43: 10 | E43: 5 | H43: 4 | I43: =E43+F43-G43-H43 -> 1 | J43: =C43*I43 -> 200
A44: 42 | B44: J&B RARE SCOTCH 1 LTR | C44: 150 | D44: 10 | E44: 7 | H44: 7 | I44: =E44+F44-G44-H44 -> 0 | J44: =C44*I44 -> 0
A45: 43 | B45: D/H CLARNET SELECT 5LTR | C45: 200 | D45: 4 | E45: 1 | H45: 1 | I45: =E45+F45-G45-H45 -> 0 | J45: =C45*I45 -> 0
A46: 44 | B46: D/H PREM GRN CRU 5LTR | C46: 200 | D46: 4 | E46: 1 | H46: 1 | I46: =E46+F46-G46-H46 -> 0 | J46: =C46*I46 -> 0
A47: 45 | B47: MARTINI BIANCO 1 LTR | C47: 150 | D47: 7 | E47: 2 | H47: 2 | I47: =E47+F47-G47-H47 -> 0 | J47: =C47*I47 -> 0
A48: 46 | B48: SMIRNOFF R/L 1 LTR | C48: 100 | D48: 8 | E48: 4 | F48: 6 | H48: 10 | I48: =E48+F48-G48-H48 -> 0 | J48: =C48*I48 -> 0
A49: 47 | B49: STOLICHNAYA VODKA LTR | C49: 100 | D49: 8 | E49: 4 | H49: 4 | I49: =E49+F49-G49-H49 -> 0 | J49: =C49*I49 -> 0
A50: 48 | B50: RUSSIAN STD. PETERS L | C50: 150 | D50: 6 | E50: 7 | H50: 7 | I50: =E50+F50-G50-H50 -> 0 | J50: =C50*I50 -> 0
A51: 49 | B51: JAGERMEISTER 1 LTR | C51: 200 | D51: 10 | E51: 4 | H51: 4 | I51: =E51+F51-G51-H51 -> 0 | J51: =C51*I51 -> 0
A52: 50 | B52: BELVEDERE VODKA LTR | C52: 200 | D52: 10 | E52: 7 | H52: 7 | I52: =E52+F52-G52-H52 -> 0 | J52: =C52*I52 -> 0
A53: 51 | B53: GREY GOOSE VODKA LTR | C53: 200 | D53: 15 | E53: 8 | H53: 8 | I53: =E53+F53-G53-H53 -> 0 | J53: =C53*I53 -> 0
A54: 52 | B54: BELUGA NOBLE VODKA 70CL | C54: 250 | D54: 4 | E54: 3 | H54: 3 | I54: =E54+F54-G54-H54 -> 0 | J54: =C54*I54 -> 0
A55: 53 | B55: CIROK VODKA LTR | C55: 300 | D55: 2 | E55: 2 | H55: 2 | I55: =E55+F55-G55-H55 -> 0 | J55: =C55*I55 -> 0
A56: 54 | B56: SKYY VODKA 1 LTR | C56: 150 | D56: 4 | E56: 2 | H56: 2 | I56: =E56+F56-G56-H56 -> 0 | J56: =C56*I56 -> 0
A57: 55 | B57: ARAK TOUMA 50/54CL | C57: 100 | D57: 2 | E57: 0 | H57: 0 | I57: =E57+F57-G57-H57 -> 0 | J57: =C57*I57 -> 0
A58: 56 | B58: EFE Fresh Grape RAKI LTR Green | C58: 150 | D58: 4 | E58: 2 | H58: 2 | I58: =E58+F58-G58-H58 -> 0 | J58: =C58*I58 -> 0
A59: 57 | B59: J/W GOLD LABEL RESERV 1 | C59: 350 | D59: 2 | E59: 2 | F59: 2 | H59: 4 | I59: =E59+F59-G59-H59 -> 0 | J59: =C59*I59 -> 0
A60: 58 | B60: J/W DOUBLE BLACK LTR | C60: 250 | D60: 6 | E60: 5 | H60: 5 | I60: =E60+F60-G60-H60 -> 0 | J60: =C60*I60 -> 0
A61: 59 | B61: J/W BLUE LABEL 1 LTR | C61: 1400 | D61: 2 | E61: 1 | H61: 1 | I61: =E61+F61-G61-H61 -> 0 | J61: =C61*I61 -> 0
A62: 60 | B62: HENNESSY VS LTR | C62: 400 | D62: 3 | E62: 2 | H62: 2 | I62: =E62+F62-G62-H62 -> 0 | J62: =C62*I62 -> 0
A63: 61 | B63: HENNESSY V.S.O.P 1 LTR Pr | C63: 500 | D63: 3 | E63: 2 | H63: 2 | I63: =E63+F63-G63-H63 -> 0 | J63: =C63*I63 -> 0
A64: 62 | B64: HENNESSY XO LTR | C64: 1600 | D64: 1 | E64: 1 | H64: 1 | I64: =E64+F64-G64-H64 -> 0 | J64: =C64*I64 -> 0
A65: 63 | B65: REMY MARTIN VSOP LTR | C65: 400 | D65: 1 | E65: 0 | H65: 0 | I65: =E65+F65-G65-H65 -> 0 | J65: =C65*I65 -> 0
A66: 64 | B66: CHIVAS 18 YRS LTR | C66: 400 | D66: 3 | E66: 4 | H66: 4 | I66: =E66+F66-G66-H66 -> 0 | J66: =C66*I66 -> 0
A67: 65 | B67: ROYAL SALUTE 21 YRS LTR | C67: 1300 | D67: 0 | E67: 1 | H67: 1 | I67: =E67+F67-G67-H67 -> 0 | J67: =C67*I67 -> 0
A68: 66 | B68: PATRON COFFE | C68: 250 | D68: 0 | E68: 0 | H68: 0 | I68: =E68+F68-G68-H68 -> 0 | J68: =C68*I68 -> 0
A69: 67 | B69: PATRON SILVER 75CL TEQUI | C69: 350 | D69: 3 | E69: 3 | H69: 3 | I69: =E69+F69-G69-H69 -> 0 | J69: =C69*I69 -> 0
A70: 68 | B70: PATRON ANEJO 75CL GOLD T | C70: 400 | D70: 3 | E70: 4 | H70: 4 | I70: =E70+F70-G70-H70 -> 0 | J70: =C70*I70 -> 0
A71: 69 | B71: DON JULIO BLANCO 70/75CL | C71: 400 | D71: 3 | E71: 3 | H71: 3 | I71: =E71+F71-G71-H71 -> 0 | J71: =C71*I71 -> 0
... A75: 73 | B75: ASTI MARTINI 75CL | C75: 150 | D75: 4 | E75: 6 | H75: 6 | I75: =E75+F75-G75-H75 -> 0 | J75: =C75*I75 -> 0
A76: 74 | B76: JC CHARDONNAY PINOT NOIR | C76: 100 | D76: 4 | E76: 2 | F76: 4 | H76: 4 | I76: =E76+F76-G76-H76 -> 2 | J76: =C76*I76 -> 200
A77: 75 | B77: BOTTEGA VINO D POET PROS | C77: 150 | D77: 1 | E77: 4 | H77: 4 | I77: =E77+F77-G77-H77 -> 0 | J77: =C77*I77 -> 0
A78: 76 | B78: BOTTEGA ROSE Proseco POE | C78: 200 | D78: 1 | E78: 9 | H78: 9 | I78: =E78+F78-G78-H78 -> 0 | J78: =C78*I78 -> 0
A79: 77 | B79: BOTTEGA GOLD BRUT 75C vi | C79: 250 | D79: 1 | E79: 4 | H79: 4 | I79: =E79+F79-G79-H79 -> 0 | J79: =C79*I79 -> 0
A80: 78 | B80: VEUVE CLICQUOT Y/L PONSR | C80: 450 | D80: 1 | E80: 3 | H80: 3 | I80: =E80+F80-G80-H80 -> 0 | J80: =C80*I80 -> 0
A81: 79 | B81: MOET & CHANDON BRUT IMP | C81: 300 | D81: 4 | E81: 4 | H81: 4 | I81: =E81+F81-G81-H81 -> 0 | J81: =C81*I81 -> 0
A82: 80 | B82: MOET & CHANDON ROSE 75CL | C82: 400 | D82: 3 | E82: 3 | H82: 3 | I82: =E82+F82-G82-H82 -> 0 | J82: =C82*I82 -> 0
A83: 81 | B83: MOET ICE IMPERIAL 75cl | C83: 500 | D83: 1 | E83: 5 | H83: 5 | I83: =E83+F83-G83-H83 -> 0 | J83: =C83*I83 -> 0
A84: 82 | B84: DOM PERIGNON M&C 75CL | C84: 1500 | D84: 1 | E84: 1 | H84: 1 | I84: =E84+F84-G84-H84 -> 0 | J84: =C84*I84 -> 0
A85: 83 | B85: GLENDFIDICH SPL R12YRS | C85: 300 | D85: 2 | E85: 1 | H85: 1 | I85: =E85+F85-G85-H85 -> 0 | J85: =C85*I85 -> 0
A86: 84 | B86: GLENDFIDICH 15 YRS LTR | C86: 400 | D86: 2 | E86: 0 | H86: 0 | I86: =E86+F86-G86-H86 -> 0 | J86: =C86*I86 -> 0
A87: 85 | B87: GLENDFIDICH 18Y Smal Bat | C87: 500 | D87: 2 | E87: 0 | F87: 1 | H87: 0 | I87: =E87+F87-G87-H87 -> 1 | J87: =C87*I87 -> 500
A88: 86 | B88: BARON RIMAPERE SAUV BLAN | C88: 200 | D88: 3 | E88: 5 | H88: 5 | I88: =E88+F88-G88-H88 -> 0 | J88: =C88*I88 -> 0
A89: 87 | B89: MARCHESI GAVI D GAVI 75C | C89: 200 | D89: 2 | E89: 4 | H89: 4 | I89: =E89+F89-G89-H89 -> 0 | J89: =C89*I89 -> 0
A90: 88 | B90: LAROCHE CHABLIS ST MARTI | C90: 200 | D90: 4 | E90: 0 | H90: 0 | I90: =E90+F90-G90-H90 -> 0 | J90: =C90*I90 -> 0
A91: 89 | B91: L J BOURGOGNE BL Cuv D ja | C91: 200 | D91: 2 | E91: 3 | F91: 3 | H91: 6 | I91: =E91+F91-G91-H91 -> 0 | J91: =C91*I91 -> 0
A92: 90 | B92: CASTEL CH. BARREYRES HAUT M 75 | C92: 150 | D92: 1 | E92: 6 | H92: 6 | I92: =E92+F92-G92-H92 -> 0 | J92: =C92*I92 -> 0
A93: 91 | B93: CH SAINT LEON BOX SUP 75 | C93: 100 | D93: 4 | E93: 8 | H93: 8 | I93: =E93+F93-G93-H93 -> 0 | J93: =C93*I93 -> 0
A94: 92 | B94: CAMPO VIEJO RESERVA RIOJ | C94: 150 | D94: 2 | E94: 6 | H94: 6 | I94: =E94+F94-G94-H94 -> 0 | J94: =C94*I94 -> 0
A95: 93 | B95: CAMPO VIEJO GRAN RESERVA | C95: 200 | D95: 2 | E95: 4 | F95: 2 | H95: 6 | I95: =E95+F95-G95-H95 -> 0 | J95: =C95*I95 -> 0
A96: 94 | B96: M MINUTY ROSE PROVENCE | C96: 150 | D96: 4 | E96: 6 | H96: 6 | I96: =E96+F96-G96-H96 -> 0 | J96: =C96*I96 -> 0
A97: 95 | B97: Cav D ESCLN WHISPERING | C97: 200 | D97: 2 | E97: 6 | H97: 6 | I97: =E97+F97-G97-H97 -> 0 | J97: =C97*I97 -> 0
A98: 96 | B98: JACK DANIELS HONEY LTR | C98: 250 | D98: 3 | E98: 1 | H98: 1 | I98: =E98+F98-G98-H98 -> 0 | J98: =C98*I98 -> 0
A99: 97 | B99: BACCARDI BREEZER W/MELON | C99: 300 | D99: 2 | E99: 2 | H99: 2 | I99: =E99+F99-G99-H99 -> 0 | J99: =C99*I99 -> 0
A100: 98 | B100: ASAHI BEER BTLS SUPER DR | C100: 300 | D100: 1 | E100: 0.5 | F100: 1.5 | H100: 2 | I100: =E100+F100-G100-H100 -> 0 | J100: =C100*I100 -> 0
A101: 99 | B101: APEROLE Aperitivo LTR | C101: 150 | D101: 2 | E101: 1 | H101: 1 | I101: =E101+F101-G101-H101 -> 0 | J101: =C101*I101 -> 0
A102: 100 | B102: CHIVAS 25 YRS | C102: 1500 | D102: 1 | E102: 0 | F102: 1 | H102: 1 | I102: =E102+F102-G102-H102 -> 0 | J102: =C102*I102 -> 0
A103: 101 | B103: CLASE AZUL Reposado 70/7 | C103: 1800 | D103: 1 | E103: 2 | H103: 2 | I103: =E103+F103-G103-H103 -> 0 | J103: =C103*I103 -> 0
...

Sheet Bussines Bay
A1: B2 Bussines Bay
A2: № | B2: Наименование товара | C2: ЦЕНА | D2: НОРМА | E2: ОСТАТОК ПРОШЛОГО ДНЯ | F2: ПРИХОД | G2: ПЕРЕМЕЩЕНИЕ | H2: ОСТАТОК ДОМА | I2: ПРОДАЖА | J2: СУММА | K2: ЗАЯВКА | L2: Доп к заявке | M2: ОСТАТОК ТЕКУЩЕГО ДНЯ
A3: 1 | B3: ABSOLUT BLUE LTR | C3: 100 | D3: 40 | E3: 20 | F3: 30 | H3: 47 | I3: =E3+F3-G3-H3 -> 3 | J3: =C3*I3 -> 300
A4: 2 | B4: J/W RED LABEL 1 LTR | C4: 100 | D4: 40 | E4: 28 | F4: 24 | H4: 48 | I4: =E4+F4-G4-H4 -> 4 | J4: =C4*I4 -> 400
A5: 3 | B5: J/W BLAK LABEL 1 LTR | C5: 200 | D5: 20 | E5: 15 | F5: 5 | H5: 19 | I5: =E5+F5-G5-H5 -> 1 | J5: =C5*I5 -> 200
A6: 4 | B6: JACK DANIELS LTR | C6: 200 | D6: 20 | E6: 19 | F6: 1 | H6: 19 | I6: =E6+F6-G6-H6 -> 1 | J6: =C6*I6 -> 200
A7: 5 | B7: CHIVAS REGAL 1 LTR | C7: 200 | D7: 20 | E7: 17 | F7: 3 | H7: 19 | I7: =E7+F7-G7-H7 -> 1 | J7: =C7*I7 -> 200
A8: 6 | B8: HEINEKEN BEER CANS 33CL | C8: 200 | D8: 15 | E8: 5 | F8: 7 | H8: 11 | I8: =E8+F8-G8-H8 -> 1 | J8: =C8*I8 -> 200
A9: 7 | B9: BUDWEISER BEER CAN 33/35 | C9: 200 | D9: 12 | E9: 7 | F9: 6 | H9: 12.5 | I9: =E9+F9-G9-H9 -> 0.5 | J9: =C9*I9 -> 100
A10: 8 | B10: CARLSBERG 50CL Can | C10: 200 | D10: 8 | E10: 3.5 | F10: 8 | H10: 11.5 | I10: =E10+F10-G10-H10 -> 0 | J10: =C10*I10 -> 0
A11: 9 | B11: RED HORSE 50CL Can | C11: 200 | D11: 5 | E11: 2 | F11: 1 | H11: 2.5 | I11: =E11+F11-G11-H11 -> 0.5 | J11: =C11*I11 -> 100
A12: 10 | B12: AMSTEL LIGHT Slim Can 35 | C12: 200 | D12: 5 | E12: 3 | H12: 3 | I12: =E12+F12-G12-H12 -> 0 | J12: =C12*I12 -> 0
A13: 11 | B13: CORONA BEER BTL 35.5CL | C13: 300 | D13: 10 | E13: 1.5 | F13: 12 | H13: 11.5 | I13: =E13+F13-G13-H13 -> 2 | J13: =C13*I13 -> 600
A14: 12 | B14: STELLA 33CL BTLS | C14: 300 | D14: 2 | E14: 2.5 | F14: 0.5 | H14: 3 | I14: =E14+F14-G14-H14 -> 0 | J14: =C14*I14 -> 0
A15: 13 | B15: STELLA ARTOIS 33 CL cans | C15: 200 | D15: 5 | E15: 2 | H15: 2 | I15: =E15+F15-G15-H15 -> 0 | J15: =C15*I15 -> 0
A16: 14 | B16: HEINEKEN BEER BTL 33CL | C16: 300 | D16: 1.5 | E16: 2 | F16: 1 | H16: 3 | I16: =E16+F16-G16-H16 -> 0 | J16: =C16*I16 -> 0
A17: 15 | B17: BUDWEISER BERR BTL 33cl | C17: 300 | D17: 1.5 | E17: 3 | H17: 3 | I17: =E17+F17-G17-H17 -> 0 | J17: =C17*I17 -> 0
A18: 16 | B18: SMIRNOFF ICE RED 27,5CL | C18: 300 | D18: 1.5 | E18: 1.5 | F18: 1.5 | H18: 2.5 | I18: =E18+F18-G18-H18 -> 0.5 | J18: =C18*I18 -> 150
A19: 17 | B19: PERONI NASTRO AZURO BEER | C19: 300 | D19: 1 | E19: 2.5 | F19: 0.5 | H19: 3 | I19: =E19+F19-G19-H19 -> 0 | J19: =C19*I19 -> 0
A20: 18 | B20: JC CHARDONNAY 75CL | C20: 100 | D20: 20 | E20: 0 | H20: 0 | I20: =E20+F20-G20-H20 -> 0 | J20: =C20*I20 -> 0
A21: 19 | B21: JC SHIRAZ CABARNET 75CL | C21: 100 | D21: 20 | E21: 16 | F21: 6 | H21: 22 | I21: =E21+F21-G21-H21 -> 0 | J21: =C21*I21 -> 0
A22: 20 | B22: CES PINOT GRIG D VEN FIO | C22: 100 | D22: 20 | E22: 14 | F22: 6 | H22: 19 | I22: =E22+F22-G22-H22 -> 1 | J22: =C22*I22 -> 100
A23: 21 | B23: Le GRAND Noir SAUV BLANC | C23: 100 | D23: 20 | E23: 5 | F23: 18 | H23: 22 | I23: =E23+F23-G23-H23 -> 1 | J23: =C23*I23 -> 100
A24: 22 | B24: Le GRAND Noir MERLOT 75C | C24: 100 | D24: 15 | E24: 12 | F24: 3 | H24: 15 | I24: =E24+F24-G24-H24 -> 0 | J24: =C24*I24 -> 0
A25: 23 | B25: MIP Collection ROSE Provienc 7 | C25: 150 | D25: 3 | E25: 4 | H25: 4 | I25: =E25+F25-G25-H25 -> 0 | J25: =C25*I25 -> 0
A26: 24 | B26: CH KSARA SUNSET ROSE 75C | C26: 100 | D26: 15 | E26: 12 | H26: 12 | I26: =E26+F26-G26-H26 -> 0 | J26: =C26*I26 -> 0
A27: 25 | B27: MATEUS ROSE 75CL | C27: 100 | D27: 15 | E27: 11 | F27: 2 | H27: 13 | I27: =E27+F27-G27-H27 -> 0 | J27: =C27*I27 -> 0
A28: 26 | B28: BACARDI WHITE RUM LTR | C28: 100 | D28: 15 | E28: 9 | F28: 1 | H28: 10 | I28: =E28+F28-G28-H28 -> 0 | J28: =C28*I28 -> 0
A29: 27 | B29: BACARDI BLACK. 1 LTR | C29: 100 | D29: 6 | E29: 9 | F29: 1 | H29: 9 | I29: =E29+F29-G29-H29 -> 1 | J29: =C29*I29 -> 100
A30: 28 | B30: BACARDI GOLD LTR | C30: 100 | D30: 8 | E30: 7 | F30: 3 | H30: 10 | I30: =E30+F30-G30-H30 -> 0 | J30: =C30*I30 -> 0
A31: 29 | B31: JOSE CUERVO GOLD LTR | C31: 100 | D31: 10 | E31: 10 | H31: 7 | I31: =E31+F31-G31-H31 -> 3 | J31: =C31*I31 -> 300
A32: 30 | B32: JOSE CUERVO SILVER Espec | C32: 100 | D32: 10 | E32: 9 | F32: 1 | H32: 10 | I32: =E32+F32-G32-H32 -> 0 | J32: =C32*I32 -> 0
A33: 31 | B33: TANQUERAY GIN LTR | C33: 200 | D33: 2 | E33: 2 | H33: 2 | I33: =E33+F33-G33-H33 -> 0 | J33: =C33*I33 -> 0
A34: 32 | B34: GORDONS PINK GIN Ltr | C34: 150 | D34: 6 | E34: 4 | H34: 4 | I34: =E34+F34-G34-H34 -> 0 | J34: =C34*I34 -> 0
A35: 33 | B35: GORDONS GIN LTR | C35: 100 | D35: 12 | E35: 10 | H35: 10 | I35: =E35+F35-G35-H35 -> 0 | J35: =C35*I35 -> 0
A36: 34 | B36: BOMBAY SAPPHIRE GIN LTR | C36: 150 | D36: 12 | E36: 7 | F36: 3 | H36: 9 | I36: =E36+F36-G36-H36 -> 1 | J36: =C36*I36 -> 150
A37: 35 | B37: HENDRICKS GIN 1 LTR | C37: 250 | D37: 10 | E37: 9 | F37: 2 | H37: 10 | I37: =E37+F37-G37-H37 -> 1 | J37: =C37*I37 -> 250
A38: 36 | B38: CAPTAIN MORGAN BLK LTR | C38: 150 | D38: 3 | E38: 6 | H38: 6 | I38: =E38+F38-G38-H38 -> 0 | J38: =C38*I38 -> 0
A39: 37 | B39: CAPTAIN MORGAN SPICED GO | C39: 150 | D39: 3 | E39: 5 | H39: 5 | I39: =E39+F39-G39-H39 -> 0 | J39: =C39*I39 -> 0
A40: 38 | B40: MALIBU WHITHE RUM LTR | C40: 150 | D40: 5 | E40: 5 | H40: 5 | I40: =E40+F40-G40-H40 -> 0 | J40: =C40*I40 -> 0
A41: 39 | B41: BAILEYS IRISH CREAM LTR | C41: 150 | D41: 6 | E41: 4 | H41: 4 | I41: =E41+F41-G41-H41 -> 0 | J41: =C41*I41 -> 0
A42: 40 | B42: AMARULA CREAM LTR | C42: 150 | D42: 2 | E42: 4 | H42: 4 | I42: =E42+F42-G42-H42 -> 0 | J42: =C42*I42 -> 0
A43: 41 | B43: JAMESON IRISH WSK LTR | C43: 200 | D43: 10 | E43: 10 | H43: 8 | I43: =E43+F43-G43-H43 -> 2 | J43: =C43*I43 -> 400
A44: 42 | B44: J&B RARE SCOTCH 1 LTR | C44: 150 | D44: 10 | E44: 10 | H44: 10 | I44: =E44+F44-G44-H44 -> 0 | J44: =C44*I44 -> 0
A45: 43 | B45: D/H CLARNET SELECT 5LTR | C45: 200 | D45: 4 | E45: 4 | H45: 4 | I45: =E45+F45-G45-H45 -> 0 | J45: =C45*I45 -> 0
A46: 44 | B46: D/H PREM GRN CRU 5LTR | C46: 200 | D46: 4 | E46: 3 | H46: 3 | I46: =E46+F46-G46-H46 -> 0 | J46: =C46*I46 -> 0
A47: 45 | B47: MARTINI BIANCO 1 LTR | C47: 150 | D47: 7 | E47: 4 | H47: 4 | I47: =E47+F47-G47-H47 -> 0 | J47: =C47*I47 -> 0
A48: 46 | B48: SMIRNOFF R/L 1 LTR | C48: 100 | D48: 8 | E48: 1 | F48: 10 | H48: 11 | I48: =E48+F48-G48-H48 -> 0 | J48: =C48*I48 -> 0
A49: 47 | B49: STOLICHNAYA VODKA LTR | C49: 100 | D49: 8 | E49: 9 | H49: 9 | I49: =E49+F49-G49-H49 -> 0 | J49: =C49*I49 -> 0
A50: 48 | B50: RUSSIAN STD. PETERS L | C50: 150 | D50: 6 | E50: 3 | H50: 3 | I50: =E50+F50-G50-H50 -> 0 | J50: =C50*I50 -> 0
A51: 49 | B51: JAGERMEISTER 1 LTR | C51: 200 | D51: 10 | E51: 8 | H51: 8 | I51: =E51+F51-G51-H51 -> 0 | J51: =C51*I51 -> 0
A52: 50 | B52: BELVEDERE VODKA LTR | C52: 200 | D52: 10 | E52: 11 | H52: 11 | I52: =E52+F52-G52-H52 -> 0 | J52: =C52*I52 -> 0
A53: 51 | B53: GREY GOOSE VODKA LTR | C53: 200 | D53: 15 | E53: 9 | F53: 15 | H53: 19 | I53: =E53+F53-G53-H53 -> 5 | J53: =C53*I53 -> 1000
A54: 52 | B54: BELUGA NOBLE VODKA 70CL | C54: 250 | D54: 4 | E54: 5 | H54: 5 | I54: =E54+F54-G54-H54 -> 0 | J54: =C54*I54 -> 0
A55: 53 | B55: CIROK VODKA LTR | C55: 300 | D55: 2 | E55: 5 | H55: 5 | I55: =E55+F55-G55-H55 -> 0 | J55: =C55*I55 -> 0
A56: 54 | B56: SKYY VODKA 1 LTR | C56: 150 | D56: 4 | E56: 6 | H56: 6 | I56: =E56+F56-G56-H56 -> 0 | J56: =C56*I56 -> 0
A57: 55 | B57: ARAK TOUMA 50/54CL | C57: 100 | D57: 2 | E57: 4 | H57: 4 | I57: =E57+F57-G57-H57 -> 0 | J57: =C57*I57 -> 0
A58: 56 | B58: EFE Fresh Grape RAKI LTR Green | C58: 150 | D58: 4 | E58: 4 | H58: 4 | I58: =E58+F58-G58-H58 -> 0 | J58: =C58*I58 -> 0
A59: 57 | B59: J/W GOLD LABEL RESERV 1 | C59: 350 | D59: 2 | E59: 6 | H59: 6 | I59: =E59+F59-G59-H59 -> 0 | J59: =C59*I59 -> 0
A60: 58 | B60: J/W DOUBLE BLACK LTR | C60: 300 | D60: 6 | E60: 1 | F60: 5 | H60: 6 | I60: =E60+F60-G60-H60 -> 0 | J60: =C60*I60 -> 0
A61: 59 | B61: J/W BLUE LABEL 1 LTR | C61: 1400 | D61: 2 | E61: 2 | H61: 2 | I61: =E61+F61-G61-H61 -> 0 | J61: =C61*I61 -> 0
A62: 60 | B62: HENNESSY VS LTR | C62: 400 | D62: 3 | E62: 4 | H62: 4 | I62: =E62+F62-G62-H62 -> 0 | J62: =C62*I62 -> 0
A63: 61 | B63: HENNESSY V.S.O.P 1 LTR Pr | C63: 500 | D63: 3 | E63: 3 | H63: 3 | I63: =E63+F63-G63-H63 -> 0 | J63: =C63*I63 -> 0
A64: 62 | B64: HENNESSY XO LTR | C64: 1600 | D64: 1 | E64: 2 | H64: 2 | I64: =E64+F64-G64-H64 -> 0 | J64: =C64*I64 -> 0
A65: 63 | B65: REMY MARTIN VSOP LTR | C65: 400 | D65: 1 | E65: 4 | H65: 4 | I65: =E65+F65-G65-H65 -> 0 | J65: =C65*I65 -> 0
A66: 64 | B66: CHIVAS 18 YRS LTR | C66: 400 | D66: 3 | E66: 4 | F66: 4 | H66: 8 | I66: =E66+F66-G66-H66 -> 0 | J66: =C66*I66 -> 0
A67: 65 | B67: ROYAL SALUTE 21 YRS LTR | C67: 1300 | D67: 0 | E67: 3 | H67: 3 | I67: =E67+F67-G67-H67 -> 0 | J67: =C67*I67 -> 0
A68: 66 | B68: PATRON COFFE | C68: 250 | D68: 0 | E68: 0 | H68: 0 | I68: =E68+F68-G68-H68 -> 0 | J68: =C68*I68 -> 0
A69: 67 | B69: PATRON SILVER 75CL TEQUI | C69: 350 | D69: 3 | E69: 5 | F69: 1 | H69: 6 | I69: =E69+F69-G69-H69 -> 0 | J69: =C69*I69 -> 0
A70: 68 | B70: PATRON ANEJO 75CL GOLD T | C70: 400 | D70: 3 | E70: 6 | H70: 6 | I70: =E70+F70-G70-H70 -> 0 | J70: =C70*I70 -> 0
A71: 69 | B71: DON JULIO BLANCO 70/75CL | C71: 400 | D71: 3 | E71: 4 | F71: 1 | H71: 5 | I71: =E71+F71-G71-H71 -> 0 | J71: =C71*I71 -> 0
A72: 70 | B72: DON JULIO REPOSADO 70/75 | C72: 450 | D72: 3 | E72: 6 | H72: 6 | I72: =E72+F72-G72-H72 -> 0 | J72: =C72*I72 -> 0
A73: 71 | B73: DON JULIO ANEJO 70/75CL | C73: 550 | D73: 3 | E73: 1 | F73: 4 | H73: 5 | I73: =E73+F73-G73-H73 -> 0 | J73: =C73*I73 -> 0
A74: 72 | B74: DON JULIO 1942 ANEJO 70 | C74: 1600 | D74: 2 | E74: 2 | F74: 1 | H74: 3 | I74: =E74+F74-G74-H74 -> 0 | J74: =C74*I74 -> 0
A75: 73 | B75: ASTI MARTINI 75CL | C75: 150 | D75: 4 | E75: 9 | H75: 9 | I75: =E75+F75-G75-H75 -> 0 | J75: =C75*I75 -> 0
A76: 74 | B76: JC CHARDONNAY PINOT NOIR | C76: 100 | D76: 4 | E76: 8 | H76: 8 | I76: =E76+F76-G76-H76 -> 0 | J76: =C76*I76 -> 0
A77: 75 | B77: BOTTEGA VINO D POET PROS | C77: 150 | D77: 1 | E77: 5 | F77: 2 | H77: 7 | I77: =E77+F77-G77-H77 -> 0 | J77: =C77*I77 -> 0
A78: 76 | B78: BOTTEGA ROSE Proseco POE | C78: 200 | D78: 1 | E78: 4 | H78: 4 | I78: =E78+F78-G78-H78 -> 0 | J78: =C78*I78 -> 0
A79: 77 | B79: BOTTEGA GOLD BRUT 75C vi | C79: 250 | D79: 1 | E79: 4 | H79: 3 | I79: =E79+F79-G79-H79 -> 1 | J79: =C79*I79 -> 250
A80: 78 | B80: VEUVE CLICQUOT Y/L PONSR | C80: 450 | D80: 1 | E80: 5 | H80: 5 | I80: =E80+F80-G80-H80 -> 0 | J80: =C80*I80 -> 0
A81: 79 | B81: MOET & CHANDON BRUT IMP | C81: 300 | D81: 4 | E81: 9 | F81: 6 | H81: 15 | I81: =E81+F81-G81-H81 -> 0 | J81: =C81*I81 -> 0
A82: 80 | B82: MOET & CHANDON ROSE 75CL | C82: 400 | D82: 3 | E82: 7 | H82: 7 | I82: =E82+F82-G82-H82 -> 0 | J82: =C82*I82 -> 0
A83: 81 | B83: MOET ICE IMPERIAL 75cl | C83: 500 | D83: 1 | E83: 4 | H83: 4 | I83: =E83+F83-G83-H83 -> 0 | J83: =C83*I83 -> 0
A84: 82 | B84: DOM PERIGNON M&C 75CL | C84: 1500 | D84: 1 | E84: 4 | H84: 4 | I84: =E84+F84-G84-H84 -> 0 | J84: =C84*I84 -> 0
A85: 83 | B85: GLENDFIDICH SPL R12YRS | C85: 300 | D85: 2 | E85: 4 | H85: 4 | I85: =E85+F85-G85-H85 -> 0 | J85: =C85*I85 -> 0
A86: 84 | B86: GLENDFIDICH 15 YRS LTR | C86: 400 | D86: 2 | E86: 1 | H86: 1 | I86: =E86+F86-G86-H86 -> 0 | J86: =C86*I86 -> 0
A87: 85 | B87: GLENDFIDICH 18Y Smal Bat | C87: 500 | D87: 2 | E87: 3 | H87: 3 | I87: =E87+F87-G87-H87 -> 0 | J87: =C87*I87 -> 0
A88: 86 | B88: BARON RIMAPERE SAUV BLAN | C88: 200 | D88: 3 | E88: 7 | H88: 7 | I88: =E88+F88-G88-H88 -> 0 | J88: =C88*I88 -> 0
A89: 87 | B89: MARCHESI GAVI D GAVI 75C | C89: 200 | D89: 2 | E89: 5 | F89: 2 | H89: 7 | I89: =E89+F89-G89-H89 -> 0 | J89: =C89*I89 -> 0
A90: 88 | B90: LAROCHE CHABLIS ST MARTI | C90: 200 | D90: 4 | E90: 0 | H90: 0 | I90: =E90+F90-G90-H90 -> 0 | J90: =C90*I90 -> 0
A91: 89 | B91: L J BOURGOGNE BL Cuv D ja | C91: 200 | D91: 2 | E91: 7 | F91: 1 | H91: 8 | I91: =E91+F91-G91-H91 -> 0 | J91: =C91*I91 -> 0
A92: 90 | B92: CASTEL CH. BARREYRES HAUT M 75 | C92: 150 | D92: 1 | E92: 5 | H92: 5 | I92: =E92+F92-G92-H92 -> 0 | J92: =C92*I92 -> 0
A93: 91 | B93: CH SAINT LEON BOX SUP 75 | C93: 100 | D93: 4 | E93: 12 | H93: 12 | I93: =E93+F93-G93-H93 -> 0 | J93: =C93*I93 -> 0
A94: 92 | B94: CAMPO VIEJO RESERVA RIOJ | C94: 150 | D94: 2 | E94: 5 | F94: 2 | H94: 7 | I94: =E94+F94-G94-H94 -> 0 | J94: =C94*I94 -> 0
A95: 93 | B95: CAMPO VIEJO GRAN RESERVA | C95: 200 | D95: 2 | E95: 5 | F95: 2 | H95: 7 | I95: =E95+F95-G95-H95 -> 0 | J95: =C95*I95 -> 0
A96: 94 | B96: M MINUTY ROSE PROVENCE | C96: 150 | D96: 4 | E96: 7 | H96: 7 | I96: =E96+F96-G96-H96 -> 0 | J96: =C96*I96 -> 0
A97: 95 | B97: Cav D ESCLN WHISPERING | C97: 200 | D97: 2 | E97: 7 | H97: 7 | I97: =E97+F97-G97-H97 -> 0 | J97: =C97*I97 -> 0
A98: 96 | B98: JACK DANIELS HONEY LTR | C98: 250 | D98: 3 | E98: 3 | H98: 3 | I98: =E98+F98-G98-H98 -> 0 | J98: =C98*I98 -> 0
A99: 97 | B99: BACCARDI BREEZER W/MELON | C99: 300 | D99: 2 | E99: 3 | H99: 2.5 | I99: =E99+F99-G99-H99 -> 0.5 | J99: =C99*I99 -> 150
A100: 98 | B100: ASAHI BEER BTLS SUPER DR | C100: 300 | D100: 1 | E100: 2.5 | F100: 0.5 | H100: 3 | I100: =E100+F100-G100-H100 -> 0 | J100: =C100*I100 -> 0
...

Sheet Selicon
A1: B3 Silicon Oasis
A2: № | B2: Наименование товара | C2: ЦЕНА | D2: НОРМА | E2: ОСТАТОК ПРОШЛОГО ДНЯ | F2: ПРИХОД | G2: ПЕРЕМЕЩЕНИЕ | H2: ОСТАТОК ДОМА | I2: ПРОДАЖА | J2: СУММА | K2: ЗАЯВКА | L2: Доп к заявке | M2: ОСТАТОК ТЕКУЩЕГО ДНЯ
A3: 1 | B3: ABSOLUT BLUE LTR | C3: 100 | D3: 40 | E3: 38 | H3: 37 | I3: =E3+F3-G3-H3 -> 1 | J3: =C3*I3 -> 100
A4: 2 | B4: J/W RED LABEL 1 LTR | C4: 100 | D4: 40 | E4: 33 | H4: 31 | I4: =E4+F4-G4-H4 -> 2 | J4: =C4*I4 -> 200
A5: 3 | B5: J/W BLAK LABEL 1 LTR | C5: 200 | D5: 20 | E5: 12 | H5: 12 | I5: =E5+F5-G5-H5 -> 0 | J5: =C5*I5 -> 0
A6: 4 | B6: JACK DANIELS LTR | C6: 200 | D6: 20 | E6: 15 | H6: 15 | I6: =E6+F6-G6-H6 -> 0 | J6: =C6*I6 -> 0
A7: 5 | B7: CHIVAS REGAL 1 LTR | C7: 200 | D7: 20 | E7: 11 | H7: 10 | I7: =E7+F7-G7-H7 -> 1 | J7: =C7*I7 -> 200
A8: 6 | B8: HEINEKEN BEER CANS 33CL | C8: 200 | D8: 15 | E8: 16.5 | H8: 16.5 | I8: =E8+F8-G8-H8 -> 0 | J8: =C8*I8 -> 0
A9: 7 | B9: BUDWEISER BEER CAN 33/35 | C9: 200 | D9: 12 | E9: 8.5 | H9: 7 | I9: =E9+F9-G9-H9 -> 1.5 | J9: =C9*I9 -> 300
A10: 8 | B10: CARLSBERG 50CL Can | C10: 200 | D10: 8 | E10: 7.5 | H10: 5.5 | I10: =E10+F10-G10-H10 -> 2 | J10: =C10*I10 -> 400
A11: 9 | B11: RED HORSE 50CL Can | C11: 200 | D11: 5 | E11: 5.5 | H11: 5 | I11: =E11+F11-G11-H11 -> 0.5 | J11: =C11*I11 -> 100
A12: 10 | B12: AMSTEL LIGHT Slim Can 35 | C12: 200 | D12: 5 | E12: 3.5 | H12: 3.5 | I12: =E12+F12-G12-H12 -> 0 | J12: =C12*I12 -> 0
A13: 11 | B13: CORONA BEER BTL 35.5CL | C13: 300 | D13: 10 | E13: 5 | H13: 4 | I13: =E13+F13-G13-H13 -> 1 | J13: =C13*I13 -> 300
A14: 12 | B14: STELLA 33CL BTLS | C14: 300 | D14: 2 | E14: 2 | H14: 2 | I14: =E14+F14-G14-H14 -> 0 | J14: =C14*I14 -> 0
... A124: 122 | B124: OYSTER BAY SAUVIGNON | C124: 150 | D124: 6 | E124: 4 | H124: 4 | I124: =E124+F124-G124-H124 -> 0 | J124: =C124*I124 -> 0
J125: =SUM(J3:J124) -> 3000
C128: Имя водителя | F128: Азиз | G128: Фариддун | L128: Сверка с итогами продаж день (должно быть 0,00)
C129: ВЫРУЧКА | F129: 2300 | G129: 1200 | L129: =(E129+F129+G129+H129+I129+J129+K129)-J125 -> 500
C130: Расходы на питание | F130: 80 | G130: 80
C131: Мы вернули долг
C132: Мы должны | E132: alawin | F132: 500
C133: Клиент вернул долг
C134: Клиент взял в долг
C135: Скидки
C136: бензин | F136: 175 | G136: 100
C137: праздник
C138: для дома
C139: мойка
C140: тонировка
D141: охрана
C143: СДАЛ | F143: 2045 | G143: 1020
C144: ДОЛЖЕН СДАТЬ | F144: =F129-F130-F131+F133-F134-F135-F136-F137-F138-F139-F140-F141-F142 -> 2045 | G144: =G129-G130-G131+G133-G134-G135-G136-G137-G138-G139-G140-G141-G142 -> 1020 | H144: =H129-H130-H131+H132+H133-H134-H135-H136-H137-H138-H139-H140-H141-H142 -> 0 | I144: =I129-I130-I131+I132+I133-I134-I135-I136-I137-I138-I139-I140-I141-I142 -> 0 | J144: =J129-J130-J131+J132+J133-J134-J135-J136-J137-J138-J139-J140-J141-J142 -> 0 | K144: =K129-K130-K131+K132+K133-K134-K135-K136-K137-K138-K139-K140-K141-K142 -> 0
C145: Плюс +/- Недостача | F145: =F143-F144 -> 0 | G145: =G143-G144 -> 0 | H145: =H143-H144 -> 0 | I145: =I143-I144 -> 0 | J145: =J143-J144 -> 0 | K145: =K143-K144 -> 0
H146: ИТОГО ОБЩАЯ Плюс +/- Недостача | K146: =E145+F145+G145+H145+I145+J145+K145 -> 0
E148: ИТОГО СУММА ПРОДАЖ | G148: =J125 -> 3000
E149: ИТОГО СДАЛИ СУММА ДЕНЬ | G149: =E143+F143+G143+H143+I143+J143+K143 -> 3065

Sheet Al-Qusais
A1: B4 Al Qusais
A2: № | B2: Наименование товара | C2: ЦЕНА | D2: НОРМА | E2: ОСТАТОК ПРОШЛОГО ДНЯ | F2: ПРИХОД | G2: ПЕРЕМЕЩЕНИЕ | H2: ОСТАТОК ДОМА | I2: ПРОДАЖА | J2: СУММА | K2: ЗАЯВКА | L2: Доп к заявке | M2: ОСТАТОК ТЕКУЩЕГО ДНЯ
A3: 1 | B3: ABSOLUT BLUE LTR | C3: 100 | D3: 40 | E3: 26 | F3: 18 | H3: 37 | I3: =E3+F3-G3-H3 -> 7 | J3: =C3*I3 -> 700
A4: 2 | B4: J/W RED LABEL 1 LTR | C4: 100 | D4: 40 | E4: 18 | F4: 27 | H4: 43 | I4: =E4+F4-G4-H4 -> 2 | J4: =C4*I4 -> 200
A5: 3 | B5: J/W BLAK LABEL 1 LTR | C5: 200 | D5: 20 | E5: 12 | F5: 6 | H5: 16 | I5: =E5+F5-G5-H5 -> 2 | J5: =C5*I5 -> 400
A6: 4 | B6: JACK DANIELS LTR | C6: 200 | D6: 20 | E6: 12 | F6: 3 | H6: 15 | I6: =E6+F6-G6-H6 -> 0 | J6: =C6*I6 -> 0
A7: 5 | B7: CHIVAS REGAL 1 LTR | C7: 200 | D7: 20 | E7: 9 | F7: 5 | H7: 12 | I7: =E7+F7-G7-H7 -> 2 | J7: =C7*I7 -> 400
A8: 6 | B8: HEINEKEN BEER CANS 33CL | C8: 200 | D8: 15 | E8: 7.5 | F8: 5.5 | H8: 11 | I8: =E8+F8-G8-H8 -> 2 | J8: =C8*I8 -> 400
A9: 7 | B9: BUDWEISER BEER CAN 33/35 | C9: 200 | D9: 12 | E9: 11.5 | F9: 2.5 | H9: 14 | I9: =E9+F9-G9-H9 -> 0 | J9: =C9*I9 -> 0
A10: 8 | B10: CARLSBERG 50CL Can | C10: 200 | D10: 8 | E10: 11 | F10: 3 | H10: 13.5 | I10: =E10+F10-G10-H10 -> 0.5 | J10: =C10*I10 -> 100
A11: 9 | B11: RED HORSE 50CL Can | C11: 200 | D11: 5 | E11: 3.5 | F11: 1 | H11: 4.5 | I11: =E11+F11-G11-H11 -> 0 | J11: =C11*I11 -> 0
A12: 10 | B12: AMSTEL LIGHT Slim Can 35 | C12: 200 | D12: 5 | E12: 1.5 | F12: 0.5 | H12: 2 | I12: =E12+F12-G12-H12 -> 0 | J12: =C12*I12 -> 0
A13: 11 | B13: CORONA BEER BTL 35.5CL | C13: 300 | D13: 10 | E13: 4.5 | F13: 2.5 | H13: 6.5 | I13: =E13+F13-G13-H13 -> 0.5 | J13: =C13*I13 -> 150
A14: 12 | B14: STELLA 33CL BTLS | C14: 300 | D14: 2 | E14: 1 | H14: 1 | I14: =E14+F14-G14-H14 -> 0 | J14: =C14*I14 -> 0
A15: 13 | B15: STELLA ARTOIS 33 CL cans | C15: 200 | D15: 5 | E15: 2 | H15: 2 | I15: =E15+F15-G15-H15 -> 0 | J15: =C15*I15 -> 0
A16: 14 | B16: HEINEKEN BEER BTL 33CL | C16: 300 | D16: 1.5 | E16: 0.5 | F16: 0.5 | H16: 1 | I16: =E16+F16-G16-H16 -> 0 | J16: =C16*I16 -> 0
A17: 15 | B17: BUDWEISER BERR BTL 33cl | C17: 300 | D17: 1.5 | E17: 1 | H17: 1 | I17: =E17+F17-G17-H17 -> 0 | J17: =C17*I17 -> 0
A18: 16 | B18: SMIRNOFF ICE RED 27,5CL | C18: 300 | D18: 1.5 | E18: 1 | H18: 1 | I18: =E18+F18-G18-H18 -> 0 | J18: =C18*I18 -> 0
A19: 17 | B19: PERONI NASTRO AZURO BEER | C19: 300 | D19: 1 | E19: 1 | H19: 1 | I19: =E19+F19-G19-H19 -> 0 | J19: =C19*I19 -> 0
A20: 18 | B20: JC CHARDONNAY 75CL | C20: 100 | D20: 20 | E20: 2 | H20: 2 | I20: =E20+F20-G20-H20 -> 0 | J20: =C20*I20 -> 0
A21: 19 | B21: JC SHIRAZ CABARNET 75CL | C21: 100 | D21: 20 | E21: 9 | F21: 1 | H21: 10 | I21: =E21+F21-G21-H21 -> 0 | J21: =C21*I21 -> 0
A22: 20 | B22: CES PINOT GRIG D VEN FIO | C22: 100 | D22: 20 | E22: 6 | H22: 6 | I22: =E22+F22-G22-H22 -> 0 | J22: =C22*I22 -> 0
A23: 21 | B23: Le GRAND Noir SAUV BLANC | C23: 100 | D23: 20 | E23: 9 | H23: 8 | I23: =E23+F23-G23-H23 -> 1 | J23: =C23*I23 -> 100
A24: 22 | B24: Le GRAND Noir MERLOT 75C | C24: 100 | D24: 15 | E24: 10 | H24: 10 | I24: =E24+F24-G24-H24 -> 0 | J24: =C24*I24 -> 0
A25: 23 | B25: MIP Collection ROSE Provienc 7 | C25: 150 | D25: 3 | E25: 0 | H25: 0 | I25: =E25+F25-G25-H25 -> 0 | J25: =C25*I25 -> 0
A26: 24 | B26: CH KSARA SUNSET ROSE 75C | C26: 100 | D26: 15 | E26: 6 | H26: 6 | I26: =E26+F26-G26-H26 -> 0 | J26: =C26*I26 -> 0
A27: 25 | B27: MATEUS ROSE 75CL | C27: 100 | D27: 15 | E27: 9 | H27: 9 | I27: =E27+F27-G27-H27 -> 0 | J27: =C27*I27 -> 0
A28: 26 | B28: BACARDI WHITE RUM LTR | C28: 100 | D28: 15 | E28: 10 | H28: 10 | I28: =E28+F28-G28-H28 -> 0 | J28: =C28*I28 -> 0
A29: 27 | B29: BACARDI BLACK. 1 LTR | C29: 100 | D29: 6 | E29: 10 | H29: 10 | I29: =E29+F29-G29-H29 -> 0 | J29: =C29*I29 -> 0
A30: 28 | B30: BACARDI GOLD LTR | C30: 100 | D30: 8 | E30: 10 | H30: 10 | I30: =E30+F30-G30-H30 -> 0 | J30: =C30*I30 -> 0
A31: 29 | B31: JOSE CUERVO GOLD LTR | C31: 100 | D31: 10 | E31: 7 | F31: 1 | H31: 8 | I31: =E31+F31-G31-H31 -> 0 | J31: =C31*I31 -> 0
A32: 30 | B32: JOSE CUERVO SILVER Espec | C32: 100 | D32: 10 | E32: 9 | F32: 1 | H32: 10 | I32: =E32+F32-G32-H32 -> 0 | J32: =C32*I32 -> 0
A33: 31 | B33: TANQUERAY GIN LTR | C33: 200 | D33: 2 | E33: 0 | H33: 0 | I33: =E33+F33-G33-H33 -> 0 | J33: =C33*I33 -> 0
A34: 32 | B34: GORDONS PINK GIN Ltr | C34: 150 | D34: 6 | E34: 2 | H34: 2 | I34: =E34+F34-G34-H34 -> 0 | J34: =C34*I34 -> 0
A35: 33 | B35: GORDONS GIN LTR | C35: 100 | D35: 12 | E35: 10 | H35: 10 | I35: =E35+F35-G35-H35 -> 0 | J35: =C35*I35 -> 0
A36: 34 | B36: BOMBAY SAPPHIRE GIN LTR | C36: 150 | D36: 12 | E36: 6 | F36: 2 | H36: 8 | I36: =E36+F36-G36-H36 -> 0 | J36: =C36*I36 -> 0
A37: 35 | B37: HENDRICKS GIN 1 LTR | C37: 250 | D37: 10 | E37: 5 | H37: 5 | I37: =E37+F37-G37-H37 -> 0 | J37: =C37*I37 -> 0
A38: 36 | B38: CAPTAIN MORGAN BLK LTR | C38: 150 | D38: 3 | E38: 3 | H38: 3 | I38: =E38+F38-G38-H38 -> 0 | J38: =C38*I38 -> 0
A39: 37 | B39: CAPTAIN MORGAN SPICED GO | C39: 150 | D39: 3 | E39: 3 | H39: 3 | I39: =E39+F39-G39-H39 -> 0 | J39: =C39*I39 -> 0
A40: 38 | B40: MALIBU WHITHE RUM LTR | C40: 150 | D40: 5 | E40: 3 | H40: 3 | I40: =E40+F40-G40-H40 -> 0 | J40: =C40*I40 -> 0
A41: 39 | B41: BAILEYS IRISH CREAM LTR | C41: 150 | D41: 6 | E41: 3 | H41: 3 | I41: =E41+F41-G41-H41 -> 0 | J41: =C41*I41 -> 0
A42: 40 | B42: AMARULA CREAM LTR | C42: 150 | D42: 2 | E42: 2 | H42: 2 | I42: =E42+F42-G42-H42 -> 0 | J42: =C42*I42 -> 0
A43: 41 | B43: JAMESON IRISH WSK LTR | C43: 200 | D43: 10 | E43: 6 | F43: 1 | H43: 7 | I43: =E43+F43-G43-H43 -> 0 | J43: =C43*I43 -> 0
A44: 42 | B44: J&B RARE SCOTCH 1 LTR | C44: 150 | D44: 10 | E44: 7 | H44: 7 | I44: =E44+F44-G44-H44 -> 0 | J44: =C44*I44 -> 0
A45: 43 | B45: D/H CLARNET SELECT 5LTR | C45: 200 | D45: 4 | E45: 1 | H45: 1 | I45: =E45+F45-G45-H45 -> 0 | J45: =C45*I45 -> 0
A46: 44 | B46: D/H PREM GRN CRU 5LTR | C46: 200 | D46: 4 | E46: 1 | H46: 1 | I46: =E46+F46-G46-H46 -> 0 | J46: =C46*I46 -> 0
A47: 45 | B47: MARTINI BIANCO 1 LTR | C47: 150 | D47: 7 | E47: 2 | H47: 2 | I47: =E47+F47-G47-H47 -> 0 | J47: =C47*I47 -> 0
A48: 46 | B48: SMIRNOFF R/L 1 LTR | C48: 100 | D48: 8 | E48: 3 | F48: 3 | H48: 6 | I48: =E48+F48-G48-H48 -> 0 | J48: =C48*I48 -> 0
A49: 47 | B49: STOLICHNAYA VODKA LTR | C49: 100 | D49: 8 | E49: 7 | H49: 7 | I49: =E49+F49-G49-H49 -> 0 | J49: =C49*I49 -> 0
A50: 48 | B50: RUSSIAN STD. PETERS L | C50: 150 | D50: 6 | E50: 6 | H50: 6 | I50: =E50+F50-G50-H50 -> 0 | J50: =C50*I50 -> 0
A51: 49 | B51: JAGERMEISTER 1 LTR | C51: 200 | D51: 10 | E51: 6 | H51: 6 | I51: =E51+F51-G51-H51 -> 0 | J51: =C51*I51 -> 0
A52: 50 | B52: BELVEDERE VODKA LTR | C52: 200 | D52: 10 | E52: 7 | H52: 7 | I52: =E52+F52-G52-H52 -> 0 | J52: =C52*I52 -> 0
A53: 51 | B53: GREY GOOSE VODKA LTR | C53: 200 | D53: 15 | E53: 10 | F53: 2 | H53: 12 | I53: =E53+F53-G53-H53 -> 0 | J53: =C53*I53 -> 0
A54: 52 | B54: BELUGA NOBLE VODKA 70CL | C54: 250 | D54: 4 | E54: 3 | H54: 3 | I54: =E54+F54-G54-H54 -> 0 | J54: =C54*I54 -> 0
A55: 53 | B55: CIROK VODKA LTR | C55: 300 | D55: 2 | E55: 2 | H55: 2 | I55: =E55+F55-G55-H55 -> 0 | J55: =C55*I55 -> 0
A56: 54 | B56: SKYY VODKA 1 LTR | C56: 150 | D56: 4 | E56: 3 | H56: 3 | I56: =E56+F56-G56-H56 -> 0 | J56: =C56*I56 -> 0
A57: 55 | B57: ARAK TOUMA 50/54CL | C57: 100 | D57: 2 | E57: 5 | H57: 5 | I57: =E57+F57-G57-H57 -> 0 | J57: =C57*I57 -> 0
A58: 56 | B58: EFE Fresh Grape RAKI LTR Green | C58: 150 | D58: 4 | E58: 3 | H58: 3 | I58: =E58+F58-G58-H58 -> 0 | J58: =C58*I58 -> 0
A59: 57 | B59: J/W GOLD LABEL RESERV 1 | C59: 350 | D59: 2 | E59: 9 | F59: 1 | H59: 10 | I59: =E59+F59-G59-H59 -> 0 | J59: =C59*I59 -> 0
A60: 58 | B60: J/W DOUBLE BLACK LTR | C60: 250 | D60: 6 | E60: 10 | H60: 10 | I60: =E60+F60-G60-H60 -> 0 | J60: =C60*I60 -> 0
A61: 59 | B61: J/W BLUE LABEL 1 LTR | C61: 1400 | D61: 2 | E61: 0 | H61: 0 | I61: =E61+F61-G61-H61 -> 0 | J61: =C61*I61 -> 0
A62: 60 | B62: HENNESSY VS LTR | C62: 400 | D62: 3 | E62: 2 | H62: 2 | I62: =E62+F62-G62-H62 -> 0 | J62: =C62*I62 -> 0
A63: 61 | B63: HENNESSY V.S.O.P 1 LTR Pr | C63: 500 | D63: 3 | E63: 2 | H63: 2 | I63: =E63+F63-G63-H63 -> 0 | J63: =C63*I63 -> 0
A64: 62 | B64: HENNESSY XO LTR | C64: 1600 | D64: 1 | E64: 0 | H64: 0 | I64: =E64+F64-G64-H64 -> 0 | J64: =C64*I64 -> 0
A65: 63 | B65: REMY MARTIN VSOP LTR | C65: 400 | D65: 1 | E65: 1 | H65: 1 | I65: =E65+F65-G65-H65 -> 0 | J65: =C65*I65 -> 0
A66: 64 | B66: CHIVAS 18 YRS LTR | C66: 400 | D66: 3 | E66: 4 | F66: 1 | H66: 5 | I66: =E66+F66-G66-H66 -> 0 | J66: =C66*I66 -> 0
A67: 65 | B67: ROYAL SALUTE 21 YRS LTR | C67: 1300 | D67: 0 | E67: 0 | H67: 0 | I67: =E67+F67-G67-H67 -> 0 | J67: =C67*I67 -> 0
A68: 66 | B68: PATRON COFFE | C68: 250 | D68: 0 | E68: 0 | H68: 0 | I68: =E68+F68-G68-H68 -> 0 | J68: =C68*I68 -> 0
A69: 67 | B69: PATRON SILVER 75CL TEQUI | C69: 350 | D69: 3 | E69: 2 | H69: 2 | I69: =E69+F69-G69-H69 -> 0 | J69: =C69*I69 -> 0
A70: 68 | B70: PATRON ANEJO 75CL GOLD T | C70: 400 | D70: 3 | E70: 2 | H70: 2 | I70: =E70+F70-G70-H70 -> 0 | J70: =C70*I70 -> 0
A71: 69 | B71: DON JULIO BLANCO 70/75CL | C71: 400 | D71: 3 | E71: 2 | H71: 2 | I71: =E71+F71-G71-H71 -> 0 | J71: =C71*I71 -> 0
A72: 70 | B72: DON JULIO REPOSADO 70/75 | C72: 450 | D72: 3 | E72: 2 | H72: 2 | I72: =E72+F72-G72-H72 -> 0 | J72: =C72*I72 -> 0
A73: 71 | B73: DON JULIO ANEJO 70/75CL | C73: 550 | D73: 3 | E73: 2 | H73: 2 | I73: =E73+F73-G73-H73 -> 0 | J73: =C73*I73 -> 0
A74: 72 | B74: DON JULIO 1942 ANEJO 70 | C74: 1600 | D74: 2 | E74: 0 | H74: 0 | I74: =E74+F74-G74-H74 -> 0 | J74: =C74*I74 -> 0
A75: 73 | B75: ASTI MARTINI 75CL | C75: 150 | D75: 4 | E75: 2 | H75: 2 | I75: =E75+F75-G75-H75 -> 0 | J75: =C75*I75 -> 0
A76: 74 | B76: JC CHARDONNAY PINOT NOIR | C76: 100 | D76: 4 | E76: 2 | H76: 2 | I76: =E76+F76-G76-H76 -> 0 | J76: =C76*I76 -> 0
A77: 75 | B77: BOTTEGA VINO D POET PROS | C77: 150 | D77: 1 | E77: 2 | H77: 2 | I77: =E77+F77-G77-H77 -> 0 | J77: =C77*I77 -> 0
A78: 76 | B78: BOTTEGA ROSE Proseco POE | C78: 200 | D78: 1 | E78: 2 | H78: 2 | I78: =E78+F78-G78-H78 -> 0 | J78: =C78*I78 -> 0
... A80: 78 | B80: VEUVE CLICQUOT Y/L PONSR | C80: 450 | D80: 1 | E80: 1 | H80: 1 | I80: =E80+F80-G80-H80 -> 0 | J80: =C80*I80 -> 0
A81: 79 | B81: MOET & CHANDON BRUT IMP | C81: 300 | D81: 4 | E81: 1 | F81: 1 | H81: 2 | I81: =E81+F81-G81-H81 -> 0 | J81: =C81*I81 -> 0
A82: 80 | B82: MOET & CHANDON ROSE 75CL | C82: 400 | D82: 3 | E82: 3 | H82: 3 | I82: =E82+F82-G82-H82 -> 0 | J82: =C82*I82 -> 0
A83: 81 | B83: MOET ICE IMPERIAL 75cl | C83: 500 | D83: 1 | E83: 1 | H83: 1 | I83: =E83+F83-G83-H83 -> 0 | J83: =C83*I83 -> 0
A84: 82 | B84: DOM PERIGNON M&C 75CL | C84: 1500 | D84: 1 | E84: 0 | H84: 0 | I84: =E84+F84-G84-H84 -> 0 | J84: =C84*I84 -> 0
A85: 83 | B85: GLENDFIDICH SPL R12YRS | C85: 300 | D85: 2 | E85: 3 | F85: 2 | H85: 5 | I85: =E85+F85-G85-H85 -> 0 | J85: =C85*I85 -> 0
A86: 84 | B86: GLENDFIDICH 15 YRS LTR | C86: 400 | D86: 2 | E86: 0 | H86: 0 | I86: =E86+F86-G86-H86 -> 0 | J86: =C86*I86 -> 0
A87: 85 | B87: GLENDFIDICH 18Y Smal Bat | C87: 500 | D87: 2 | E87: 2 | H87: 2 | I87: =E87+F87-G87-H87 -> 0 | J87: =C87*I87 -> 0
A88: 86 | B88: BARON RIMAPERE SAUV BLAN | C88: 200 | D88: 3 | E88: 5 | H88: 5 | I88: =E88+F88-G88-H88 -> 0 | J88: =C88*I88 -> 0
A89: 87 | B89: MARCHESI GAVI D GAVI 75C | C89: 200 | D89: 2 | E89: 5 | H89: 5 | I89: =E89+F89-G89-H89 -> 0 | J89: =C89*I89 -> 0
A90: 88 | B90: LAROCHE CHABLIS ST MARTI | C90: 200 | D90: 4 | E90: 0 | H90: 0 | I90: =E90+F90-G90-H90 -> 0 | J90: =C90*I90 -> 0
A91: 89 | B91: L J BOURGOGNE BL Cuv D ja | C91: 200 | D91: 2 | E91: 7 | H91: 7 | I91: =E91+F91-G91-H91 -> 0 | J91: =C91*I91 -> 0
A92: 90 | B92: CASTEL CH. BARREYRES HAUT M 75 | C92: 150 | D92: 1 | E92: 5 | H92: 5 | I92: =E92+F92-G92-H92 -> 0 | J92: =C92*I92 -> 0
A93: 91 | B93: CH SAINT LEON BOX SUP 75 | C93: 100 | D93: 4 | E93: 6 | H93: 6 | I93: =E93+F93-G93-H93 -> 0 | J93: =C93*I93 -> 0
A94: 92 | B94: CAMPO VIEJO RESERVA RIOJ | C94: 150 | D94: 2 | E94: 3 | H94: 3 | I94: =E94+F94-G94-H94 -> 0 | J94: =C94*I94 -> 0
A95: 93 | B95: CAMPO VIEJO GRAN RESERVA | C95: 200 | D95: 2 | E95: 3 | H95: 3 | I95: =E95+F95-G95-H95 -> 0 | J95: =C95*I95 -> 0
A96: 94 | B96: M MINUTY ROSE PROVENCE | C96: 150 | D96: 4 | E96: 2 | H96: 2 | I96: =E96+F96-G96-H96 -> 0 | J96: =C96*I96 -> 0
A97: 95 | B97: Cav D ESCLN WHISPERING | C97: 200 | D97: 2 | E97: 5 | H97: 5 | I97: =E97+F97-G97-H97 -> 0 | J97: =C97*I97 -> 0
... A112: 110 | B112: MACALLAN 12 YR FIN TRIP | C112: 550 | D112: 1 | E112: 0 | H112: 0 | I112: =E112+F112-G112-H112 -> 0 | J112: =C112*I112 -> 0
A113: 111 | B113: MACALLAN 15 YRS Double Ca | C113: 800 | D113: 1 | E113: 0 | F113: 1 | H113: 1 | I113: =E113+F113-G113-H113 -> 0 | J113: =C113*I113 -> 0
A114: 112 | B114: MACALLAN 18 YRS | C114: 2000 | D114: 1 | E114: 0 | H114: 0 | I114: =E114+F114-G114-H114 -> 0 | J114: =C114*I114 -> 0
A115: 113 | B115: HOEGARDEN BLANCHE 33CL B | C115: 300 | D115: 1 | E115: 1 | H115: 1 | I115: =E115+F115-G115-H115 -> 0 | J115: =C115*I115 -> 0
...

Sheet Tikom
A1: B5 Tikkom
A2: № | B2: Наименование товара | C2: ЦЕНА | D2: НОРМА | E2: ОСТАТОК ПРОШЛОГО ДНЯ | F2: ПРИХОД | G2: ПЕРЕМЕЩЕНИЕ | H2: ОСТАТОК ДОМА | I2: ПРОДАЖА | J2: СУММА | K2: ЗАЯВКА | L2: Доп к заявке | M2: ОСТАТОК ТЕКУЩЕГО ДНЯ
A3: 1 | B3: ABSOLUT BLUE LTR | C3: 100 | D3: 40 | E3: 4 | F3: 26 | H3: 24 | I3: =E3+F3-G3-H3 -> 6 | J3: =C3*I3 -> 600
A4: 2 | B4: J/W RED LABEL 1 LTR | C4: 100 | D4: 40 | E4: 9 | F4: 24 | H4: 30 | I4: =E4+F4-G4-H4 -> 3 | J4: =C4*I4 -> 300
A5: 3 | B5: J/W BLAK LABEL 1 LTR | C5: 200 | D5: 20 | E5: 1 | F5: 9 | H5: 7 | I5: =E5+F5-G5-H5 -> 3 | J5: =C5*I5 -> 600
A6: 4 | B6: JACK DANIELS LTR | C6: 200 | D6: 20 | E6: 7 | H6: 6 | I6: =E6+F6-G6-H6 -> 1 | J6: =C6*I6 -> 200
A7: 5 | B7: CHIVAS REGAL 1 LTR | C7: 200 | D7: 20 | E7: 6 | H7: 6 | I7: =E7+F7-G7-H7 -> 0 | J7: =C7*I7 -> 0
A8: 6 | B8: HEINEKEN BEER CANS 33CL | C8: 200 | D8: 15 | E8: 1 | F8: 5 | H8: 4 | I8: =E8+F8-G8-H8 -> 2 | J8: =C8*I8 -> 400
A9: 7 | B9: BUDWEISER BEER CAN 33/35 | C9: 200 | D9: 12 | E9: 3.5 | F9: 1.5 | H9: 4 | I9: =E9+F9-G9-H9 -> 1 | J9: =C9*I9 -> 200
A10: 8 | B10: CARLSBERG 50CL Can | C10: 200 | D10: 8 | E10: 2.5 | F10: 3.5 | H10: 6 | I10: =E10+F10-G10-H10 -> 0 | J10: =C10*I10 -> 0
A11: 9 | B11: RED HORSE 50CL Can | C11: 200 | D11: 5 | E11: 0 | H11: 0 | I11: =E11+F11-G11-H11 -> 0 | J11: =C11*I11 -> 0
A12: 10 | B12: AMSTEL LIGHT Slim Can 35 | C12: 200 | D12: 5 | E12: 0 | H12: 0 | I12: =E12+F12-G12-H12 -> 0 | J12: =C12*I12 -> 0
A13: 11 | B13: CORONA BEER BTL 35.5CL | C13: 300 | D13: 10 | E13: 0 | F13: 7 | H13: 7 | I13: =E13+F13-G13-H13 -> 0 | J13: =C13*I13 -> 0
A14: 12 | B14: STELLA 33CL BTLS | C14: 300 | D14: 2 | E14: 0.5 | H14: 0.5 | I14: =E14+F14-G14-H14 -> 0 | J14: =C14*I14 -> 0
A15: 13 | B15: STELLA ARTOIS 33 CL cans | C15: 200 | D15: 5 | E15: 0 | H15: 0 | I15: =E15+F15-G15-H15 -> 0 | J15: =C15*I15 -> 0
A16: 14 | B16: HEINEKEN BEER BTL 33CL | C16: 300 | D16: 1.5 | E16: 0.5 | H16: 0.5 | I16: =E16+F16-G16-H16 -> 0 | J16: =C16*I16 -> 0
A17: 15 | B17: BUDWEISER BERR BTL 33cl | C17: 300 | D17: 1.5 | E17: 0.5 | H17: 0.5 | I17: =E17+F17-G17-H17 -> 0 | J17: =C17*I17 -> 0
A18: 16 | B18: SMIRNOFF ICE RED 27,5CL | C18: 300 | D18: 1.5 | E18: 0 | F18: 0.5 | H18: 0.5 | I18: =E18+F18-G18-H18 -> 0 | J18: =C18*I18 -> 0
A19: 17 | B19: PERONI NASTRO AZURO BEER | C19: 300 | D19: 1 | E19: 0.5 | H19: 0.5 | I19: =E19+F19-G19-H19 -> 0 | J19: =C19*I19 -> 0
A20: 18 | B20: JC CHARDONNAY 75CL | C20: 100 | D20: 20 | E20: 0 | H20: 0 | I20: =E20+F20-G20-H20 -> 0 | J20: =C20*I20 -> 0
A21: 19 | B21: JC SHIRAZ CABARNET 75CL | C21: 100 | D21: 20 | E21: 13 | H21: 13 | I21: =E21+F21-G21-H21 -> 0 | J21: =C21*I21 -> 0
A22: 20 | B22: CES PINOT GRIG D VEN FIO | C22: 100 | D22: 20 | E22: 5 | F22: 5 | H22: 10 | I22: =E22+F22-G22-H22 -> 0 | J22: =C22*I22 -> 0
A23: 21 | B23: Le GRAND Noir SAUV BLANC | C23: 100 | D23: 20 | E23: 2 | F23: 13 | H23: 14 | I23: =E23+F23-G23-H23 -> 1 | J23: =C23*I23 -> 100
A24: 22 | B24: Le GRAND Noir MERLOT 75C | C24: 100 | D24: 15 | E24: 4 | F24: 6 | H24: 10 | I24: =E24+F24-G24-H24 -> 0 | J24: =C24*I24 -> 0
A25: 23 | B25: MIP Collection ROSE Provienc 7 | C25: 150 | D25: 3 | E25: 2 | H25: 2 | I25: =E25+F25-G25-H25 -> 0 | J25: =C25*I25 -> 0
A26: 24 | B26: CH KSARA SUNSET ROSE 75C | C26: 100 | D26: 15 | E26: 6 | H26: 5 | I26: =E26+F26-G26-H26 -> 1 | J26: =C26*I26 -> 100
A27: 25 | B27: MATEUS ROSE 75CL | C27: 100 | D27: 15 | E27: 3 | F27: 2 | H27: 5 | I27: =E27+F27-G27-H27 -> 0 | J27: =C27*I27 -> 0
A28: 26 | B28: BACARDI WHITE RUM LTR | C28: 100 | D28: 15 | E28: 4 | H28: 4 | I28: =E28+F28-G28-H28 -> 0 | J28: =C28*I28 -> 0
A29: 27 | B29: BACARDI BLACK. 1 LTR | C29: 100 | D29: 6 | E29: 3 | H29: 3 | I29: =E29+F29-G29-H29 -> 0 | J29: =C29*I29 -> 0
A30: 28 | B30: BACARDI GOLD LTR | C30: 100 | D30: 8 | E30: 5 | H30: 4 | I30: =E30+F30-G30-H30 -> 1 | J30: =C30*I30 -> 100
A31: 29 | B31: JOSE CUERVO GOLD LTR | C31: 100 | D31: 10 | E31: 5 | H31: 5 | I31: =E31+F31-G31-H31 -> 0 | J31: =C31*I31 -> 0
A32: 30 | B32: JOSE CUERVO SILVER Espec | C32: 100 | D32: 10 | E32: 2 | F32: 3 | H32: 5 | I32: =E32+F32-G32-H32 -> 0 | J32: =C32*I32 -> 0
A33: 31 | B33: TANQUERAY GIN LTR | C33: 200 | D33: 2 | E33: 2 | H33: 2 | I33: =E33+F33-G33-H33 -> 0 | J33: =C33*I33 -> 0
A34: 32 | B34: GORDONS PINK GIN Ltr | C34: 150 | D34: 6 | E34: 2 | H34: 2 | I34: =E34+F34-G34-H34 -> 0 | J34: =C34*I34 -> 0
A35: 33 | B35: GORDONS GIN LTR | C35: 100 | D35: 12 | E35: 2 | F35: 3 | H35: 4 | I35: =E35+F35-G35-H35 -> 1 | J35: =C35*I35 -> 100
A36: 34 | B36: BOMBAY SAPPHIRE GIN LTR | C36: 150 | D36: 12 | E36: 3 | F36: 2 | H36: 4 | I36: =E36+F36-G36-H36 -> 1 | J36: =C36*I36 -> 150
A37: 35 | B37: HENDRICKS GIN 1 LTR | C37: 250 | D37: 10 | E37: 0 | F37: 5 | H37: 4 | I37: =E37+F37-G37-H37 -> 1 | J37: =C37*I37 -> 250
A38: 36 | B38: CAPTAIN MORGAN BLK LTR | C38: 150 | D38: 3 | E38: 4 | H38: 4 | I38: =E38+F38-G38-H38 -> 0 | J38: =C38*I38 -> 0
A39: 37 | B39: CAPTAIN MORGAN SPICED GO | C39: 150 | D39: 3 | E39: 0 | F39: 4 | H39: 2 | I39: =E39+F39-G39-H39 -> 2 | J39: =C39*I39 -> 300
A40: 38 | B40: MALIBU WHITHE RUM LTR | C40: 150 | D40: 5 | E40: 2 | H40: 2 | I40: =E40+F40-G40-H40 -> 0 | J40: =C40*I40 -> 0
A41: 39 | B41: BAILEYS IRISH CREAM LTR | C41: 150 | D41: 6 | E41: 4 | H41: 4 | I41: =E41+F41-G41-H41 -> 0 | J41: =C41*I41 -> 0
A42: 40 | B42: AMARULA CREAM LTR | C42: 150 | D42: 2 | E42: 1 | H42: 1 | I42: =E42+F42-G42-H42 -> 0 | J42: =C42*I42 -> 0
A43: 41 | B43: JAMESON IRISH WSK LTR | C43: 200 | D43: 10 | E43: 1 | H43: 1 | I43: =E43+F43-G43-H43 -> 0 | J43: =C43*I43 -> 0
A44: 42 | B44: J&B RARE SCOTCH 1 LTR | C44: 150 | D44: 10 | E44: 5 | H44: 5 | I44: =E44+F44-G44-H44 -> 0 | J44: =C44*I44 -> 0
A45: 43 | B45: D/H CLARNET SELECT 5LTR | C45: 200 | D45: 4 | E45: 0 | H45: 0 | I45: =E45+F45-G45-H45 -> 0 | J45: =C45*I45 -> 0
A46: 44 | B46: D/H PREM GRN CRU 5LTR | C46: 200 | D46: 4 | E46: 0 | H46: 0 | I46: =E46+F46-G46-H46 -> 0 | J46: =C46*I46 -> 0
A47: 45 | B47: MARTINI BIANCO 1 LTR | C47: 150 | D47: 7 | E47: 0 | F47: 1 | H47: 1 | I47: =E47+F47-G47-H47 -> 0 | J47: =C47*I47 -> 0
A48: 46 | B48: SMIRNOFF R/L 1 LTR | C48: 100 | D48: 8 | E48: 3 | F48: 7 | H48: 10 | I48: =E48+F48-G48-H48 -> 0 | J48: =C48*I48 -> 0
A49: 47 | B49: STOLICHNAYA VODKA LTR | C49: 100 | D49: 8 | E49: 0 | H49: 0 | I49: =E49+F49-G49-H49 -> 0 | J49: =C49*I49 -> 0
A50: 48 | B50: RUSSIAN STD. PETERS L | C50: 150 | D50: 6 | E50: 2 | H50: 2 | I50: =E50+F50-G50-H50 -> 0 | J50: =C50*I50 -> 0
A51: 49 | B51: JAGERMEISTER 1 LTR | C51: 200 | D51: 10 | E51: 4 | F51: 1 | H51: 3 | I51: =E51+F51-G51-H51 -> 2 | J51: =C51*I51 -> 400
A52: 50 | B52: BELVEDERE VODKA LTR | C52: 200 | D52: 10 | E52: 5 | H52: 5 | I52: =E52+F52-G52-H52 -> 0 | J52: =C52*I52 -> 0
A53: 51 | B53: GREY GOOSE VODKA LTR | C53: 200 | D53: 15 | E53: 5 | F53: 10 | H53: 13 | I53: =E53+F53-G53-H53 -> 2 | J53: =C53*I53 -> 400
A54: 52 | B54: BELUGA NOBLE VODKA 70CL | C54: 250 | D54: 4 | E54: 1 | H54: 1 | I54: =E54+F54-G54-H54 -> 0 | J54: =C54*I54 -> 0
A55: 53 | B55: CIROK VODKA LTR | C55: 300 | D55: 2 | E55: 1 | H55: 1 | I55: =E55+F55-G55-H55 -> 0 | J55: =C55*I55 -> 0
A56: 54 | B56: SKYY VODKA 1 LTR | C56: 150 | D56: 4 | E56: 1 | H56: 1 | I56: =E56+F56-G56-H56 -> 0 | J56: =C56*I56 -> 0
A57: 55 | B57: ARAK TOUMA 50/54CL | C57: 100 | D57: 2 | E57: 0 | H57: 0 | I57: =E57+F57-G57-H57 -> 0 | J57: =C57*I57 -> 0
A58: 56 | B58: EFE Fresh Grape RAKI LTR Green | C58: 150 | D58: 4 | E58: 0 | H58: 0 | I58: =E58+F58-G58-H58 -> 0 | J58: =C58*I58 -> 0
A59: 57 | B59: J/W GOLD LABEL RESERV 1 | C59: 350 | D59: 2 | E59: 5 | H59: 4 | I59: =E59+F59-G59-H59 -> 1 | J59: =C59*I59 -> 350
A60: 58 | B60: J/W DOUBLE BLACK LTR | C60: 250 | D60: 6 | E60: 4 | H60: 3 | I60: =E60+F60-G60-H60 -> 1 | J60: 300
A61: 59 | B61: J/W BLUE LABEL 1 LTR | C61: 1400 | D61: 2 | E61: 0 | F61: 1 | H61: 1 | I61: =E61+F61-G61-H61 -> 0 | J61: =C61*I61 -> 0
A62: 60 | B62: HENNESSY VS LTR | C62: 400 | D62: 3 | E62: 2 | H62: 2 | I62: =E62+F62-G62-H62 -> 0 | J62: =C62*I62 -> 0
A63: 61 | B63: HENNESSY V.S.O.P 1 LTR Pr | C63: 500 | D63: 3 | E63: 3 | H63: 3 | I63: =E63+F63-G63-H63 -> 0 | J63: =C63*I63 -> 0
A64: 62 | B64: HENNESSY XO LTR | C64: 1600 | D64: 1 | E64: 0 | H64: 0 | I64: =E64+F64-G64-H64 -> 0 | J64: =C64*I64 -> 0
A65: 63 | B65: REMY MARTIN VSOP LTR | C65: 400 | D65: 1 | E65: 0 | H65: 0 | I65: =E65+F65-G65-H65 -> 0 | J65: =C65*I65 -> 0
A66: 64 | B66: CHIVAS 18 YRS LTR | C66: 400 | D66: 3 | E66: 2 | F66: 4 | H66: 4 | I66: =E66+F66-G66-H66 -> 2 | J66: =C66*I66 -> 800
A67: 65 | B67: ROYAL SALUTE 21 YRS LTR | C67: 1300 | D67: 0 | E67: 0 | F67: 1 | H67: 1 | I67: =E67+F67-G67-H67 -> 0 | J67: =C67*I67 -> 0
A68: 66 | B68: PATRON COFFE | C68: 250 | D68: 0 | E68: 0 | H68: 0 | I68: =E68+F68-G68-H68 -> 0 | J68: =C68*I68 -> 0
A69: 67 | B69: PATRON SILVER 75CL TEQUI | C69: 350 | D69: 3 | E69: 3 | H69: 3 | I69: =E69+F69-G69-H69 -> 0 | J69: =C69*I69 -> 0
A70: 68 | B70: PATRON ANEJO 75CL GOLD T | C70: 400 | D70: 3 | E70: 3 | H70: 3 | I70: =E70+F70-G70-H70 -> 0 | J70: =C70*I70 -> 0
A71: 69 | B71: DON JULIO BLANCO 70/75CL | C71: 400 | D71: 3 | E71: 0 | F71: 3 | H71: 3 | I71: =E71+F71-G71-H71 -> 0 | J71: =C71*I71 -> 0
A72: 70 | B72: DON JULIO REPOSADO 70/75 | C72: 450 | D72: 3 | E72: 6 | H72: 6 | I72: =E72+F72-G72-H72 -> 0 | J72: =C72*I72 -> 0
A73: 71 | B73: DON JULIO ANEJO 70/75CL | C73: 550 | D73: 3 | E73: 3 | H73: 3 | I73: =E73+F73-G73-H73 -> 0 | J73: =C73*I73 -> 0
A74: 72 | B74: DON JULIO 1942 ANEJO 70 | C74: 1600 | D74: 2 | E74: 2 | H74: 2 | I74: =E74+F74-G74-H74 -> 0 | J74: =C74*I74 -> 0
A75: 73 | B75: ASTI MARTINI 75CL | C75: 150 | D75: 4 | E75: 6 | H75: 6 | I75: =E75+F75-G75-H75 -> 0 | J75: =C75*I75 -> 0
A76: 74 | B76: JC CHARDONNAY PINOT NOIR | C76: 100 | D76: 4 | E76: 5 | F76: 1 | H76: 4 | I76: =E76+F76-G76-H76 -> 2 | J76: =C76*I76 -> 200
A77: 75 | B77: BOTTEGA VINO D POET PROS | C77: 150 | D77: 1 | E77: 6 | H77: 6 | I77: =E77+F77-G77-H77 -> 0 | J77: =C77*I77 -> 0
A78: 76 | B78: BOTTEGA ROSE Proseco POE | C78: 200 | D78: 1 | E78: 6 | H78: 6 | I78: =E78+F78-G78-H78 -> 0 | J78: =C78*I78 -> 0
A79: 77 | B79: BOTTEGA GOLD BRUT 75C vi | C79: 250 | D79: 1 | E79: 4 | F79: 2 | H79: 6 | I79: =E79+F79-G79-H79 -> 0 | J79: =C79*I79 -> 0
A80: 78 | B80: VEUVE CLICQUOT Y/L PONSR | C80: 450 | D80: 1 | E80: 4 | H80: 4 | I80: =E80+F80-G80-H80 -> 0 | J80: =C80*I80 -> 0
A81: 79 | B81: MOET & CHANDON BRUT IMP | C81: 300 | D81: 4 | E81: 9 | H81: 9 | I81: =E81+F81-G81-H81 -> 0 | J81: =C81*I81 -> 0
A82: 80 | B82: MOET & CHANDON ROSE 75CL | C82: 400 | D82: 3 | E82: 6 | H82: 6 | I82: =E82+F82-G82-H82 -> 0 | J82: =C82*I82 -> 0
A83: 81 | B83: MOET ICE IMPERIAL 75cl | C83: 500 | D83: 1 | E83: 3 | H83: 3 | I83: =E83+F83-G83-H83 -> 0 | J83: =C83*I83 -> 0
A84: 82 | B84: DOM PERIGNON M&C 75CL | C84: 1500 | D84: 1 | E84: 2 | H84: 2 | I84: =E84+F84-G84-H84 -> 0 | J84: =C84*I84 -> 0
A85: 83 | B85: GLENDFIDICH SPL R12YRS | C85: 300 | D85: 2 | E85: 1 | H85: 1 | I85: =E85+F85-G85-H85 -> 0 | J85: =C85*I85 -> 0
A86: 84 | B86: GLENDFIDICH 15 YRS LTR | C86: 400 | D86: 2 | E86: 0 | H86: 0 | I86: =E86+F86-G86-H86 -> 0 | J86: =C86*I86 -> 0
A87: 85 | B87: GLENDFIDICH 18Y Smal Bat | C87: 500 | D87: 2 | E87: 0 | F87: 1 | H87: 1 | I87: =E87+F87-G87-H87 -> 0 | J87: =C87*I87 -> 0
A88: 86 | B88: BARON RIMAPERE SAUV BLAN | C88: 200 | D88: 3 | E88: 4 | H88: 4 | I88: =E88+F88-G88-H88 -> 0 | J88: =C88*I88 -> 0
A89: 87 | B89: MARCHESI GAVI D GAVI 75C | C89: 200 | D89: 2 | E89: 2 | F89: 4 | H89: 6 | I89: =E89+F89-G89-H89 -> 0 | J89: =C89*I89 -> 0
A90: 88 | B90: LAROCHE CHABLIS ST MARTI | C90: 200 | D90: 4 | E90: 0 | H90: 0 | I90: =E90+F90-G90-H90 -> 0 | J90: =C90*I90 -> 0
A91: 89 | B91: L J BOURGOGNE BL Cuv D ja | C91: 200 | D91: 2 | E91: 6 | H91: 6 | I91: =E91+F91-G91-H91 -> 0 | J91: =C91*I91 -> 0
A92: 90 | B92: CASTEL CH. BARREYRES HAUT M 75 | C92: 150 | D92: 1 | E92: 2 | H92: 2 | I92: =E92+F92-G92-H92 -> 0 | J92: =C92*I92 -> 0
A93: 91 | B93: CH SAINT LEON BOX SUP 75 | C93: 100 | D93: 4 | E93: 2 | F93: 7 | H93: 8 | I93: =E93+F93-G93-H93 -> 1 | J93: =C93*I93 -> 100
A94: 92 | B94: CAMPO VIEJO RESERVA RIOJ | C94: 150 | D94: 2 | E94: 8 | H94: 8 | I94: =E94+F94-G94-H94 -> 0 | J94: =C94*I94 -> 0
A95: 93 | B95: CAMPO VIEJO GRAN RESERVA | C95: 200 | D95: 2 | E95: 7 | H95: 7 | I95: =E95+F95-G95-H95 -> 0 | J95: =C95*I95 -> 0
A96: 94 | B96: M MINUTY ROSE PROVENCE | C96: 150 | D96: 4 | E96: 2 | F96: 4 | H96: 6 | I96: =E96+F96-G96-H96 -> 0 | J96: =C96*I96 -> 0
A97: 95 | B97: Cav D ESCLN WHISPERING | C97: 200 | D97: 2 | E97: 4 | F97: 2 | H97: 6 | I97: =E97+F97-G97-H97 -> 0 | J97: =C97*I97 -> 0
A98: 96 | B98: JACK DANIELS HONEY LTR | C98: 250 | D98: 3 | E98: 2 | H98: 2 | I98: =E98+F98-G98-H98 -> 0 | J98: =C98*I98 -> 0
A99: 97 | B99: BACCARDI BREEZER W/MELON | C99: 300 | D99: 2 | E99: 0 | H99: 0 | I99: =E99+F99-G99-H99 -> 0 | J99: =C99*I99 -> 0
A100: 98 | B100: ASAHI BEER BTLS SUPER DR | C100: 300 | D100: 1 | E100: 0 | F100: 2 | H100: 2 | I100: =E100+F100-G100-H100 -> 0 | J100: =C100*I100 -> 0
...

Sheet ЗАЯВКА
D2: J | E2: B | F2: S | I2: J | J2: B | K2: S
D3: B1 | E3: B2 | F3: B3 | I3: B1 | J3: B2 | K3: B3
B4: 1 | C4: ABSOLUT BLUE LTR | D4: =' JVC'!K3 -> #REF! | E4: =Tikom!K3 | F4: =Selicon!K3 | G4: 62 | H4: HENNESSY XO LTR | I4: =' JVC'!K64 -> #REF! | J4: =Tikom!K64 | K4: =Selicon!K64
B5: 2 | C5: J/W RED LABEL 1 LTR | D5: =' JVC'!K4 -> #REF! | E5: =Tikom!K4 | F5: =Selicon!K4 | G5: 63 | H5: REMY MARTIN VSOP LTR | I5: =' JVC'!K65 -> #REF! | J5: =Tikom!K65 | K5: =Selicon!K65
B6: 3 | C6: J/W BLAK LABEL 1 LTR | D6: =' JVC'!K5 -> #REF! | E6: =Tikom!K5 | F6: =Selicon!K5 | G6: 64 | H6: CHIVAS 18 YRS LTR | I6: =' JVC'!K66 -> #REF! | J6: =Tikom!K66 | K6: =Selicon!K66
B7: 4 | C7: JACK DANIELS LTR | D7: =' JVC'!K6 -> #REF! | E7: =Tikom!K6 | F7: =Selicon!K6 | G7: 65 | H7: ROYAL SALUTE 21 YRS LTR | I7: =' JVC'!K67 -> #REF! | J7: =Tikom!K67 | K7: =Selicon!K67
B8: 5 | C8: CHIVAS REGAL 1 LTR | D8: =' JVC'!K7 -> #REF! | E8: =Tikom!K7 | F8: =Selicon!K7 | G8: 66 | H8: PATRON COFFE | I8: =' JVC'!K68 -> #REF! | J8: =Tikom!K68 | K8: =Selicon!K68
B9: 6 | C9: HEINEKEN BEER CANS 33CL | D9: =' JVC'!K8 -> #REF! | E9: =Tikom!K8 | F9: =Selicon!K8 | G9: 67 | H9: PATRON SILVER 75CL TEQUI | I9: =' JVC'!K69 -> #REF! | J9: =Tikom!K69 | K9: =Selicon!K69
B10: 7 | C10: BUDWEISER BEER CAN 33/35 | D10: =' JVC'!K9 -> #REF! | E10: =Tikom!K9 | F10: =Selicon!K9 | G10: 68 | H10: PATRON ANEJO 75CL GOLD T | I10: =' JVC'!K70 -> #REF! | J10: =Tikom!K70 | K10: =Selicon!K70
B11: 8 | C11: CARLSBERG 50CL Can | D11: =' JVC'!K10 -> #REF! | E11: =Tikom!K10 | F11: =Selicon!K10 | G11: 69 | H11: DON JULIO BLANCO 70/75CL | I11: =' JVC'!K71 -> #REF! | J11: =Tikom!K71 | K11: =Selicon!K71
B12: 9 | C12: RED HORSE 50CL Can | D12: =' JVC'!K11 -> #REF! | E12: =Tikom!K11 | F12: =Selicon!K11 | G12: 70 | H12: DON JULIO REPOSADO 70/75 | I12: =' JVC'!K72 -> #REF! | J12: =Tikom!K72 | K12: =Selicon!K72
B13: 10 | C13: AMSTEL LIGHT Slim Can 35 | D13: =' JVC'!K12 -> #REF! | E13: =Tikom!K12 | F13: =Selicon!K12 | G13: 71 | H13: DON JULIO ANEJO 70/75CL | I13: =' JVC'!K73 -> #REF! | J13: =Tikom!K73 | K13: =Selicon!K73
B14: 11 | C14: CORONA BEER BTL 35.5CL | D14: =' JVC'!K13 -> #REF! | E14: =Tikom!K13 | F14: =Selicon!K13 | G14: 72 | H14: DON JULIO 1942 ANEJO 70 | I14: =' JVC'!K74 -> #REF! | J14: =Tikom!K74 | K14: =Selicon!K74
B15: 12 | C15: STELLA 33CL BTLS | D15: =' JVC'!K14 -> #REF! | E15: =Tikom!K14 | F15: =Selicon!K14 | G15: 73 | H15: ASTI MARTINI 75CL | I15: =' JVC'!K75 -> #REF! | J15: =Tikom!K75 | K15: =Selicon!K75
... B64: 61 | C64: HENNESSY V.S.O.P 1 LTR Pr | D64: =' JVC'!K63 -> #REF! | E64: =Tikom!K63 | F64: =Selicon!K63 | G64: 122 | H64: OYSTER BAY SAUVIGNON | I64: =' JVC'!K124 -> #REF! | J64: =Tikom!K124 | K64: =Selicon!K124

Sheet ДОЛГИ
D4: УЧЕТ ЗАДОЛЖЕННОСТЕЙ
D5: Мы вернули долг | F5: =' JVC'!E131+Tikom!E130+Selicon!E131+' JVC'!F131+' JVC'!G131+' JVC'!H131+' JVC'!I131+' JVC'!J131+' JVC'!K131+Tikom!F130+Tikom!G130+Tikom!H130+Tikom!I130+Tikom!J130+Tikom!K130+Selicon!F131+Selicon!G131+Selicon!H131+Selicon!I131+Selicon!J131+Selicon!K131 -> #REF!
D6: Мы должны | F6: =' JVC'!E132+' JVC'!F132+' JVC'!G132+' JVC'!H132+' JVC'!I132+' JVC'!J132+' JVC'!K132+Tikom!E131+Tikom!F131+Tikom!G131+Tikom!H131+Tikom!I131+Tikom!J131+Tikom!K131+Selicon!E132+Selicon!F132+Selicon!G132+Selicon!H132+Selicon!I132+Selicon!J132+Selicon!K132 -> #REF!
D7: Клиент вернул долг | F7: 1400
D8: Клиент взял в долг | F8: =' JVC'!E134+' JVC'!F134+' JVC'!G134+' JVC'!H134+' JVC'!I134+' JVC'!J134+' JVC'!K134+Tikom!E133+Tikom!F133+Tikom!G133+Tikom!H133+Tikom!I133+Tikom!J133+Tikom!K133+Selicon!E134+Selicon!F134+Selicon!G134+Selicon!H134+Selicon!I134+Selicon!J134+Selicon!K134 -> #REF!
D9: ИТОГО мы должны | F9: =F6-F5 -> #REF!
D10: ИТОГО нам должны | F10: =F8-F7 -> #REF!
D11: БАЛАНС (нам должны больше +/- мы должны больше) | F11: =F9-F10 -> #REF!
